Workbook

Sheet GBP01 & Convexity
B2: 10-Year Bond | F2: 30-Year Bond | J2: 10 Year Gilt
B3: Price | C3: ='10 year Gilt'!C3 -> 99.770471 | F3: Price | G3: 86.767 | J3: Change in BPs | K3: Change in BPs in Percentage | L3: New Yield | M3: Price (Full reval) | N3: PnL Full | O3: PnL DV01 | P3: PnL DV01+Conv | Q3: Error (GBP01) | R3: Error (GBP01+Conv) | T3: Change in BPs | U3: PnL Full | V3: PnL DV01 | W3: PnL DV01+Conv | Y3: Change in BPs | Z3: Error (GBP01) | AA3: Error (GBP01+Conv)
B4: Face Value | C4: 100 | F4: Face Value | G4: 100 | J4: -200 | K4: =J4/10000 -> -0.02 | L4: =K4+$C$5 -> 0.0253 | M4: 116.54341 | N4: =M4-$M$8 -> 16.772941 | O4: =-$C$34*K4*10000 -> 31.146278 | P4: =(-$M$8*$C$24*K4)+(0.5*$M$8*$C$29*(K4^2)) -> 37.50611 | Q4: =-($N4-O4) -> 14.373337 | R4: =($N4-P4) -> -20.733169 | T4: -200 | U4: 16.772941 | V4: 31.146278 | W4: 37.50611 | Y4: -200 | Z4: 14.373337 | AA4: -20.733169
B5: Yield | C5: 0.0453 | F5: Yield | G5: 0.05276 | J5: -150 | K5: =J5/10000 -> -0.015 | L5: =K5+$C$5 -> 0.0303 | M5: 112.0562 | N5: =M5-$M$8 -> 12.285734 | O5: =-$C$34*K5*10000 -> 23.359708 | P5: =(-$M$8*$C$24*K5)+(0.5*$M$8*$C$29*(K5^2)) -> 26.937675 | Q5: =-($N5-O5) -> 11.073975 | R5: =($N5-P5) -> -14.651942 | T5: -150 | U5: 12.285734 | V5: 23.359708 | W5: 26.937675 | Y5: -150 | Z5: 11.073975 | AA5: -14.651942
B6: Semi-Annually Yield | C6: =C5/2 -> 0.02265 | F6: Semi-Annually Yield | G6: =G5/2 -> 0.02638 | J6: -100 | K6: =J6/10000 -> -0.01 | L6: =K6+$C$5 -> 0.0353 | M6: 107.77147 | N6: =M6-$M$8 -> 8.0010007 | O6: =-$C$34*K6*10000 -> 15.573139 | P6: =(-$M$8*$C$24*K6)+(0.5*$M$8*$C$29*(K6^2)) -> 17.163845 | Q6: =-($N6-O6) -> 7.5721381 | R6: =($N6-P6) -> -9.1628443 | T6: -100 | U6: 8.0010007 | V6: 15.573139 | W6: 17.163845 | Y6: -100 | Z6: 7.5721381 | AA6: -9.1628443
B7: Coupon Rate | C7: 0.045 | F7: Coupon Rate | G7: 0.04375 | J7: -50 | K7: =J7/10000 -> -0.005 | L7: =K7+$C$5 -> 0.0403 | M7: 103.67935 | N7: =M7-$M$8 -> 3.9088755 | O7: =-$C$34*K7*10000 -> 7.7865694 | P7: =(-$M$8*$C$24*K7)+(0.5*$M$8*$C$29*(K7^2)) -> 8.18462 | Q7: =-($N7-O7) -> 3.8776939 | R7: =($N7-P7) -> -4.2757445 | T7: -50 | U7: 3.9088755 | V7: 7.7865694 | W7: 8.18462 | Y7: -50 | Z7: 3.8776939 | AA7: -4.2757445
B8: Coupon | C8: =C4*C7 -> 4.5 | F8: Coupon | G8: =G4*G7 -> 4.375 | J8: 0 | K8: =J8/10000 -> 0 | L8: =K8+$C$5 -> 0.0453 | M8: 99.770471 | N8: =M8-$M$8 -> 0 | O8: =-$C$34*K8*10000 -> 0 | P8: =(-$M$8*$C$24*K8)+(0.5*$M$8*$C$29*(K8^2)) -> 0 | Q8: =-($N8-O8) -> 0 | R8: =($N8-P8) -> 0 | T8: 0 | U8: 0 | V8: 0 | W8: 0 | Y8: 0 | Z8: 0 | AA8: 0
B9: Semi-Annually Coupon | C9: =C8/2 -> 2.25 | F9: Semi-Annually Coupon | G9: =G8/2 -> 2.1875 | J9: 50 | K9: =J9/10000 -> 0.005 | L9: =K9+$C$5 -> 0.0503 | M9: 96.035969 | N9: =M9-$M$8 -> -3.7345023 | O9: =-$C$34*K9*10000 -> -7.7865694 | P9: =(-$M$8*$C$24*K9)+(0.5*$M$8*$C$29*(K9^2)) -> -7.3900149 | Q9: =-($N9-O9) -> -4.0520671 | R9: =($N9-P9) -> 3.6555126 | T9: 50 | U9: -3.7345023 | V9: -7.7865694 | W9: -7.3900149 | Y9: 50 | Z9: -4.0520671 | AA9: 3.6555126
B10: Issue Date | C10: 45723 | F10: Issue Date | G10: 45869 | J10: 100 | K10: =J10/10000 -> 0.01 | L10: =K10+$C$5 -> 0.0553 | M10: 92.467418 | N10: =M10-$M$8 -> -7.3030527 | O10: =-$C$34*K10*10000 -> -15.573139 | P10: =(-$M$8*$C$24*K10)+(0.5*$M$8*$C$29*(K10^2)) -> -13.985425 | Q10: =-($N10-O10) -> -8.2700862 | R10: =($N10-P10) -> 6.6823722 | T10: 100 | U10: -7.3030527 | V10: -15.573139 | W10: -13.985425 | Y10: 100 | Z10: -8.2700862 | AA10: 6.6823722
B11: Last Coupon Payment Date | C11: =EDATE(C10,6) -> 45907 | F11: Last Coupon Payment Date | G11: =G10 -> 45869 | J11: 150 | K11: =J11/10000 -> 0.015 | L11: =K11+$C$5 -> 0.0603 | M11: 89.05683 | N11: =M11-$M$8 -> -10.713641 | O11: =-$C$34*K11*10000 -> -23.359708 | P11: =(-$M$8*$C$24*K11)+(0.5*$M$8*$C$29*(K11^2)) -> -19.78623 | Q11: =-($N11-O11) -> -12.646067 | R11: =($N11-P11) -> 9.0725884 | T11: 150 | U11: -10.713641 | V11: -23.359708 | W11: -19.78623 | Y11: 150 | Z11: -12.646067 | AA11: 9.0725884
B12: Next Coupon Payment Date | C12: =EDATE(C11,6) -> 46088 | F12: Next Coupon Payment Date | G12: =EDATE(G11,6) -> 46053 | J12: 200 | K12: =J12/10000 -> 0.02 | L12: =K12+$C$5 -> 0.0653 | M12: 85.79662 | N12: =M12-$M$8 -> -13.973851 | O12: =-$C$34*K12*10000 -> -31.146278 | P12: =(-$M$8*$C$24*K12)+(0.5*$M$8*$C$29*(K12^2)) -> -24.792429 | Q12: =-($N12-O12) -> -17.172427 | R12: =($N12-P12) -> 10.818579 | T12: 200 | U12: -13.973851 | V12: -31.146278 | W12: -24.792429 | Y12: 200 | Z12: -17.172427 | AA12: 10.818579
B13: Settlement Date | C13: 46005 | F13: Settlement Date | G13: 46005
B14: Maturity Date | C14: 49375 | F14: Maturity Date | G14: 56461
J15: 10 Year Gilt
J16: Change in BPs | K16: Change in BPs in Percentage | L16: New Yield | M16: Price (Full reval) | N16: PnL Full | O16: PnL DV01 | P16: PnL DV01+Conv | Q16: Error (GBP01) | R16: Error (GBP01+Conv) | T16: Change in BPs | U16: PnL Full | V16: PnL DV01 | W16: PnL DV01+Conv | Y16: Change in BPs | Z16: Error (GBP01) | AA16: Error (GBP01+Conv)
B17: Macaulay Duration | J17: -200 | K17: =J17/10000 -> -0.02 | L17: =K17+$G$5 -> 0.03276 | M17: 120.47328 | N17: =M17-$M$21 -> 33.778841 | O17: =-$C$35*K17*10000 -> 52.523234 | P17: =(-$M$21*$C$25*K17)+(0.5*$M$21*$C$30*(K17^2)) -> 78.767934 | Q17: =-($N17-O17) -> 18.744393 | R17: =($N17-P17) -> -44.989093 | T17: -200 | U17: 33.778841 | V17: 52.523234 | W17: 78.767934 | Y17: -200 | Z17: 18.744393 | AA17: -44.989093
B18: Bond | C18: Base | D18: Parallel Up | E18: Parallel Down | J18: -150 | K18: =J18/10000 -> -0.015 | L18: =K18+$G$5 -> 0.03776 | M18: 110.50219 | N18: =M18-$M$21 -> 23.807747 | O18: =-$C$35*K18*10000 -> 39.392426 | P18: =(-$M$21*$C$25*K18)+(0.5*$M$21*$C$30*(K18^2)) -> 54.176859 | Q18: =-($N18-O18) -> 15.584678 | R18: =($N18-P18) -> -30.369111 | T18: -150 | U18: 23.807747 | V18: 39.392426 | W18: 54.176859 | Y18: -150 | Z18: 15.584678 | AA18: -30.369111
B19: 10 Year Gilt | C19: ='10 Year Scenario'!F26 -> 16.31762 | D19: ='10 Year Scenario'!Q26 -> 15.19895 | E19: ='10 Year Scenario'!AB26 -> 17.259326 | J19: -100 | K19: =J19/10000 -> -0.01 | L19: =K19+$G$5 -> 0.04276 | M19: 101.63646 | N19: =M19-$M$21 -> 14.942023 | O19: =-$C$35*K19*10000 -> 26.261617 | P19: =(-$M$21*$C$25*K19)+(0.5*$M$21*$C$30*(K19^2)) -> 32.851845 | Q19: =-($N19-O19) -> 11.319594 | R19: =($N19-P19) -> -17.909822 | T19: -100 | U19: 14.942023 | V19: 26.261617 | W19: 32.851845 | Y19: -100 | Z19: 11.319594 | AA19: -17.909822
B20: 30 Year Gilt | C20: ='30 Year Scenario'!F66 -> 31.960931 | D20: ='30 Year Scenario'!Q66 -> 21.130289 | E20: ='30 Year Scenario'!AB66 -> 45.807244 | J20: -50 | K20: =J20/10000 -> -0.005 | L20: =K20+$G$5 -> 0.04776 | M20: 93.740017 | N20: =M20-$M$21 -> 7.0455751 | O20: =-$C$35*K20*10000 -> 13.130809 | P20: =(-$M$21*$C$25*K20)+(0.5*$M$21*$C$30*(K20^2)) -> 14.792892 | Q20: =-($N20-O20) -> 6.0852334 | R20: =($N20-P20) -> -7.7473166 | T20: -50 | U20: 7.0455751 | V20: 13.130809 | W20: 14.792892 | Y20: -50 | Z20: 6.0852334 | AA20: -7.7473166
J21: 0 | K21: =J21/10000 -> 0 | L21: =K21+$G$5 -> 0.05276 | M21: 86.694441 | N21: =M21-$M$21 -> 0 | O21: =-$C$35*K21*10000 -> 0 | P21: =(-$M$21*$C$25*K21)+(0.5*$M$21*$C$30*(K21^2)) -> 0 | Q21: =-($N21-O21) -> 0 | R21: =($N21-P21) -> 0 | T21: 0 | U21: 0 | V21: 0 | W21: 0 | Y21: 0 | Z21: 0 | AA21: 0
B22: Modified Duration | J22: 50 | K22: =J22/10000 -> 0.005 | L22: =K22+$G$5 -> 0.05776 | M22: 80.396644 | N22: =M22-$M$21 -> -6.2977975 | O22: =-$C$35*K22*10000 -> -13.130809 | P22: =(-$M$21*$C$25*K22)+(0.5*$M$21*$C$30*(K22^2)) -> -11.526831 | Q22: =-($N22-O22) -> -6.833011 | R22: =($N22-P22) -> 5.229033 | T22: 50 | U22: -6.2977975 | V22: -13.130809 | W22: -11.526831 | Y22: 50 | Z22: -6.833011 | AA22: 5.229033
B23: Bond | C23: Base | D23: Parallel Up | E23: Parallel Down | J23: 100 | K23: =J23/10000 -> 0.01 | L23: =K23+$G$5 -> 0.06276 | M23: 74.756785 | N23: =M23-$M$21 -> -11.937656 | O23: =-$C$35*K23*10000 -> -26.261617 | P23: =(-$M$21*$C$25*K23)+(0.5*$M$21*$C$30*(K23^2)) -> -19.7876 | Q23: =-($N23-O23) -> -14.323961 | R23: =($N23-P23) -> 7.8499436 | T23: 100 | U23: -11.937656 | V23: -26.261617 | W23: -19.7876 | Y23: 100 | Z23: -14.323961 | AA23: 7.8499436
B24: 10 Year Gilt | C24: ='10 Year Scenario'!F27 -> 15.610465 | D24: ='10 Year Scenario'!Q27 -> 14.540275 | E24: ='10 Year Scenario'!AB26 -> 17.259326 | J24: 150 | K24: =J24/10000 -> 0.015 | L24: =K24+$G$5 -> 0.06776 | M24: 69.696513 | N24: =M24-$M$21 -> -16.997929 | O24: =-$C$35*K24*10000 -> -39.392426 | P24: =(-$M$21*$C$25*K24)+(0.5*$M$21*$C$30*(K24^2)) -> -24.782308 | Q24: =-($N24-O24) -> -22.394497 | R24: =($N24-P24) -> 7.7843795 | T24: 150 | U24: -16.997929 | V24: -39.392426 | W24: -24.782308 | Y24: 150 | Z24: -22.394497 | AA24: 7.7843795
B25: 30 Year Gilt | C25: ='30 Year Scenario'!F67 -> 30.359181 | D25: ='30 Year Scenario'!Q67 -> 20.071326 | E25: ='30 Year Scenario'!AB67 -> 43.511574 | J25: 200 | K25: =J25/10000 -> 0.02 | L25: =K25+$G$5 -> 0.07276 | M25: 65.147435 | N25: =M25-$M$21 -> -21.547007 | O25: =-$C$35*K25*10000 -> -52.523234 | P25: =(-$M$21*$C$25*K25)+(0.5*$M$21*$C$30*(K25^2)) -> -26.510955 | Q25: =-($N25-O25) -> -30.976227 | R25: =($N25-P25) -> 4.9639485 | T25: 200 | U25: -21.547007 | V25: -52.523234 | W25: -26.510955 | Y25: 200 | Z25: -30.976227 | AA25: 4.9639485
B27: Convexity
B28: Bond | C28: Base | D28: Parallel Up | E28: Parallel Down
B29: 10 Year Gilt | C29: ='10 Year Scenario'!F28 -> 318.57324 | D29: ='10 Year Scenario'!Q28 -> 289.39741 | E29: ='10 Year Scenario'!AB28 -> 343.4445
B30: 30 Year Gilt | C30: ='30 Year Scenario'!F68 -> 1506.9299 | D30: ='30 Year Scenario'!Q68 -> 767.64579 | E30: ='30 Year Scenario'!AB68 -> 2515.8499
B32: GBP01
B33: Bond | C33: Base | D33: Parallel Up | E33: Parallel Down
B34: 10 Year Gilt | C34: ='10 Year Scenario'!F29 -> 0.15573139 | D34: ='10 Year Scenario'!Q29 -> 0.10430267 | E34: ='10 Year Scenario'!AB29 -> 0.23804087
B35: 30 Year Gilt | C35: ='30 Year Scenario'!F69 -> 0.26261617 | D35: ='30 Year Scenario'!Q69 -> 0.10843705 | E35: ='30 Year Scenario'!AB69 -> 0.92165471

Sheet 10 year Gilt
B2: 10-Year Bond | F2: Coupon Payment Date | G2: Period | H2: Cash Flow | I2: PV of CF | J2: PV as % of Sum of PV | K2: TW PV of CF | L2: TW^2 PV of CF | O2: Yield | P2: Price | Q2: Duration Implied Price | R2: Convexity Implied Price
B3: Price | C3: =I24 -> 99.770471 | F3: =C10 -> 45723 | O3: 0.01 | P3: 131.64412 | Q3: =$I$24*(1-$C$18*(O3-$C$5)) -> 152.54354 | R3: =$I$24*(1-$C$18*(O3-$C$5)+0.5*$C$19*((O3-$C$5)^2)) -> 170.71872
B4: Face Value | C4: 100 | F4: =EDATE(F3,6) -> 45907 | O4: 0.015 | P4: 126.47024 | Q4: =$I$24*(1-$C$18*(O4-$C$5)) -> 145.0686 | R4: =$I$24*(1-$C$18*(O4-$C$5)+0.5*$C$19*((O4-$C$5)^2)) -> 158.45965
B5: Yield | C5: 0.0453 | F5: =EDATE(F4,6) -> 46088 | G5: 1 | H5: =$C$9 -> 2.25 | I5: =H5/(1+$C$6)^G5 -> 2.2001662 | J5: =I5/$I$24 -> 0.022052279 | K5: =J5*G5 -> 0.022052279 | L5: =G5*(G5+1)*I5 -> 4.4003325 | O5: 0.02 | P5: 121.53251 | Q5: =$I$24*(1-$C$18*(O5-$C$5)) -> 137.59366 | R5: =$I$24*(1-$C$18*(O5-$C$5)+0.5*$C$19*((O5-$C$5)^2)) -> 146.92986
B6: Semi-Annually Yield | C6: =C5/2 -> 0.02265 | F6: =EDATE(F5,6) -> 46272 | G6: 2 | H6: =$C$9 -> 2.25 | I6: =H6/(1+$C$6)^G6 -> 2.1514362 | J6: =I6/$I$24 -> 0.021563857 | K6: =J6*G6 -> 0.043127715 | L6: =G6*(G6+1)*I6 -> 12.908617 | O6: 0.025 | P6: 116.81931 | Q6: =$I$24*(1-$C$18*(O6-$C$5)) -> 130.11872 | R6: =$I$24*(1-$C$18*(O6-$C$5)+0.5*$C$19*((O6-$C$5)^2)) -> 136.12937
B7: Coupon Rate | C7: 0.045 | F7: =EDATE(F6,6) -> 46453 | G7: 3 | H7: =$C$9 -> 2.25 | I7: =H7/(1+$C$6)^G7 -> 2.1037855 | J7: =I7/$I$24 -> 0.021086254 | K7: =J7*G7 -> 0.063258761 | L7: =G7*(G7+1)*I7 -> 25.245426 | O7: 0.03 | P7: 112.31963 | Q7: =$I$24*(1-$C$18*(O7-$C$5)) -> 122.64378 | R7: =$I$24*(1-$C$18*(O7-$C$5)+0.5*$C$19*((O7-$C$5)^2)) -> 126.05817
B8: Coupon | C8: =C4*C7 -> 4.5 | F8: =EDATE(F7,6) -> 46637 | G8: 4 | H8: =$C$9 -> 2.25 | I8: =H8/(1+$C$6)^G8 -> 2.0571901 | J8: =I8/$I$24 -> 0.020619228 | K8: =J8*G8 -> 0.082476913 | L8: =G8*(G8+1)*I8 -> 41.143802 | O8: 0.035 | P8: 108.02303 | Q8: =$I$24*(1-$C$18*(O8-$C$5)) -> 115.16885 | R8: =$I$24*(1-$C$18*(O8-$C$5)+0.5*$C$19*((O8-$C$5)^2)) -> 116.71625
B9: Semi-Annually Coupon | C9: =C8/2 -> 2.25 | F9: =EDATE(F8,6) -> 46819 | G9: 5 | H9: =$C$9 -> 2.25 | I9: =H9/(1+$C$6)^G9 -> 2.0116268 | J9: =I9/$I$24 -> 0.020162547 | K9: =J9*G9 -> 0.10081273 | L9: =G9*(G9+1)*I9 -> 60.348803 | O9: 0.04 | P9: 103.91962 | Q9: =$I$24*(1-$C$18*(O9-$C$5)) -> 107.69391 | R9: =$I$24*(1-$C$18*(O9-$C$5)+0.5*$C$19*((O9-$C$5)^2)) -> 108.10362
B10: Issue Date | C10: 45723 | F10: =EDATE(F9,6) -> 47003 | G10: 6 | H10: =$C$9 -> 2.25 | I10: =H10/(1+$C$6)^G10 -> 1.9670726 | J10: =I10/$I$24 -> 0.01971598 | K10: =J10*G10 -> 0.11829588 | L10: =G10*(G10+1)*I10 -> 82.617048 | O10: 0.045 | P10: 100 | Q10: =$I$24*(1-$C$18*(O10-$C$5)) -> 100.21897 | R10: =$I$24*(1-$C$18*(O10-$C$5)+0.5*$C$19*((O10-$C$5)^2)) -> 100.22028
B11: Last Coupon Payment Date | C11: =EDATE(C10,6) -> 45907 | F11: =EDATE(F10,6) -> 47184 | G11: 7 | H11: =$C$9 -> 2.25 | I11: =H11/(1+$C$6)^G11 -> 1.9235052 | J11: =I11/$I$24 -> 0.019279303 | K11: =J11*G11 -> 0.13495512 | L11: =G11*(G11+1)*I11 -> 107.71629 | O11: 0.05 | P11: 96.255277 | Q11: =$I$24*(1-$C$18*(O11-$C$5)) -> 92.744028 | R11: =$I$24*(1-$C$18*(O11-$C$5)+0.5*$C$19*((O11-$C$5)^2)) -> 93.066228
B12: Next Coupon Payment Date | C12: =EDATE(C11,6) -> 46088 | F12: =EDATE(F11,6) -> 47368 | G12: 8 | H12: =$C$9 -> 2.25 | I12: =H12/(1+$C$6)^G12 -> 1.8809027 | J12: =I12/$I$24 -> 0.018852299 | K12: =J12*G12 -> 0.15081839 | L12: =G12*(G12+1)*I12 -> 135.425 | O12: 0.055 | P12: 92.676999 | Q12: =$I$24*(1-$C$18*(O12-$C$5)) -> 85.269089 | R12: =$I$24*(1-$C$18*(O12-$C$5)+0.5*$C$19*((O12-$C$5)^2)) -> 86.641464
B13: Settlement Date | C13: =TODAY() -> 46006 | F13: =EDATE(F12,6) -> 47549 | G13: 9 | H13: =$C$9 -> 2.25 | I13: =H13/(1+$C$6)^G13 -> 1.8392439 | J13: =I13/$I$24 -> 0.018434752 | K13: =J13*G13 -> 0.16591276 | L13: =G13*(G13+1)*I13 -> 165.53195 | O13: 0.06 | P13: 89.257151 | Q13: =$I$24*(1-$C$18*(O13-$C$5)) -> 77.79415 | R13: =$I$24*(1-$C$18*(O13-$C$5)+0.5*$C$19*((O13-$C$5)^2)) -> 80.945988
B14: Maturity Date | C14: 49375 | F14: =EDATE(F13,6) -> 47733 | G14: 10 | H14: =$C$9 -> 2.25 | I14: =H14/(1+$C$6)^G14 -> 1.7985077 | J14: =I14/$I$24 -> 0.018026453 | K14: =J14*G14 -> 0.18026453 | L14: =G14*(G14+1)*I14 -> 197.83584 | O14: 0.065 | P14: 85.988125 | Q14: =$I$24*(1-$C$18*(O14-$C$5)) -> 70.319211 | R14: =$I$24*(1-$C$18*(O14-$C$5)+0.5*$C$19*((O14-$C$5)^2)) -> 75.9798
F15: =EDATE(F14,6) -> 47914 | G15: 11 | H15: =$C$9 -> 2.25 | I15: =H15/(1+$C$6)^G15 -> 1.7586737 | J15: =I15/$I$24 -> 0.017627197 | K15: =J15*G15 -> 0.19389916 | L15: =G15*(G15+1)*I15 -> 232.14493 | O15: 0.07 | P15: 82.862703 | Q15: =$I$24*(1-$C$18*(O15-$C$5)) -> 62.844272 | R15: =$I$24*(1-$C$18*(O15-$C$5)+0.5*$C$19*((O15-$C$5)^2)) -> 71.742901
F16: =EDATE(F15,6) -> 48098 | G16: 12 | H16: =$C$9 -> 2.25 | I16: =H16/(1+$C$6)^G16 -> 1.719722 | J16: =I16/$I$24 -> 0.017236783 | K16: =J16*G16 -> 0.2068414 | L16: =G16*(G16+1)*I16 -> 268.27663 | O16: 0.075 | P16: 79.874032 | Q16: =$I$24*(1-$C$18*(O16-$C$5)) -> 55.369333 | R16: =$I$24*(1-$C$18*(O16-$C$5)+0.5*$C$19*((O16-$C$5)^2)) -> 68.23529
B17: Macaulay Duration | C17: =K24 -> 15.663059 | F17: =EDATE(F16,6) -> 48280 | G17: 13 | H17: =$C$9 -> 2.25 | I17: =H17/(1+$C$6)^G17 -> 1.681633 | J17: =I17/$I$24 -> 0.016855017 | K17: =J17*G17 -> 0.21911522 | L17: =G17*(G17+1)*I17 -> 306.05721 | O17: 0.08 | P17: 77.015606 | Q17: =$I$24*(1-$C$18*(O17-$C$5)) -> 47.894394 | R17: =$I$24*(1-$C$18*(O17-$C$5)+0.5*$C$19*((O17-$C$5)^2)) -> 65.456967
B18: Modified Duration | C18: =C17/(1+C5) -> 14.984271 | F18: =EDATE(F17,6) -> 48464 | G18: 14 | H18: =$C$9 -> 2.25 | I18: =H18/(1+$C$6)^G18 -> 1.6443876 | J18: =I18/$I$24 -> 0.016481707 | K18: =J18*G18 -> 0.23074389 | L18: =G18*(G18+1)*I18 -> 345.3214
B19: Convexity | C19: =L24/I24 -> 292.38641 | F19: =EDATE(F18,6) -> 48645 | G19: 15 | H19: =$C$9 -> 2.25 | I19: =H19/(1+$C$6)^G19 -> 1.6079672 | J19: =I19/$I$24 -> 0.016116664 | K19: =J19*G19 -> 0.24174996 | L19: =G19*(G19+1)*I19 -> 385.91212
F20: =EDATE(F19,6) -> 48829 | G20: 16 | H20: =$C$9 -> 2.25 | I20: =H20/(1+$C$6)^G20 -> 1.5723534 | J20: =I20/$I$24 -> 0.015759707 | K20: =J20*G20 -> 0.25215531 | L20: =G20*(G20+1)*I20 -> 427.68012
F21: =EDATE(F20,6) -> 49010 | G21: 17 | H21: =$C$9 -> 2.25 | I21: =H21/(1+$C$6)^G21 -> 1.5375284 | J21: =I21/$I$24 -> 0.015410655 | K21: =J21*G21 -> 0.26198114 | L21: =G21*(G21+1)*I21 -> 470.48368
F22: =EDATE(F21,6) -> 49194 | G22: 18 | H22: =$C$9 -> 2.25 | I22: =H22/(1+$C$6)^G22 -> 1.5034746 | J22: =I22/$I$24 -> 0.015069335 | K22: =J22*G22 -> 0.27124803 | L22: =G22*(G22+1)*I22 -> 514.18833
F23: =EDATE(F22,6) -> 49375 | G23: 19 | H23: =$C$9+C4 -> 102.25 | I23: =H23/(1+$C$6)^G23 -> 66.811294 | J23: =I23/$I$24 -> 0.66964998 | K23: =J23*G23 -> 12.72335 | L23: =G23*(G23+1)*I23 -> 25388.292
I24: =SUM(I5:I23) -> 99.770471 | K24: =SUM(K5:K23) -> 15.663059 | L24: =SUM(L5:L23) -> 29171.529

Sheet 10 Year Scenario
P2: Parallel Up | Q2: 0.0025 | AA2: Parallel Down | AB2: 0.0025
B3: 10-Year Bond | E3: Period | F3: Scenario Rate | G3: Cash Flow | H3: PV of CF | I3: PV as % of CF | J3: TW PV of CF | K3: Reivestment as per theory | M3: TW^2 PV of CF | P3: Period | Q3: Scenario Rate | R3: Cash Flow | S3: PV of CF | T3: PV as % of CF | U3: TW PV of CF | V3: Reivestment as per theory | X3: TW^2 PV of CF | AA3: Period | AB3: Scenario Rate | AC3: Cash Flow | AD3: PV of CF | AE3: PV as % of CF | AF3: TW PV of CF | AG3: Reivestment as per theory | AI3: TW^2 PV of CF
B4: Price | C4: 99.809 | E4: 1 | F4: =$C$7 -> 0.02265 | G4: =$C$10 -> 2.25 | H4: =G4/(1+F4)^E4 -> 2.2001662 | I4: =H4/$H$24 -> 0.022054397 | J4: =I4*E4 -> 0.022054397 | K4: =H4*(1+F4)^($E$19-E4) -> 3.0786537 | M4: =E4*(E4+1)*H4 -> 4.4003325 | P4: 1 | Q4: =$C$7 -> 0.02265 | R4: =$C$10 -> 2.25 | S4: =R4/(1+Q4)^P4 -> 2.2001662 | T4: =S4/$S$24 -> 0.030671336 | U4: =T4*P4 -> 0.030671336 | V4: =S4*(1+Q4)^($P$18-P4) -> 3.0104666 | X4: =P4*(P4+1)*S4 -> 4.4003325 | AA4: 1 | AB4: =$C$7 -> 0.02265 | AC4: =$C$10 -> 2.25 | AD4: =AC4/(1+AB4)^AA4 -> 2.2001662 | AE4: =AD4/$AD$24 -> 0.015261136 | AF4: =AE4*AA4 -> 0.015261136 | AG4: =AD4*(1+AB4)^($P$18-AA4) -> 3.0104666 | AI4: =AA4*(AA4+1)*AD4 -> 4.4003325
B5: Face Value | C5: 100 | E5: 2 | F5: =$C$7 -> 0.02265 | G5: =$C$10 -> 2.25 | H5: =G5/(1+F5)^E5 -> 2.1514362 | I5: =H5/$H$24 -> 0.021565929 | J5: =I5*E5 -> 0.043131858 | K5: =H5*(1+F5)^($E$19-E5) -> 2.9437898 | M5: =E5*(E5+1)*H5 -> 12.908617 | P5: 2 | Q5: =Q4+$Q$2/2 -> 0.0239 | R5: =$C$10 -> 2.25 | S5: =R5/(1+Q5)^P5 -> 2.1461864 | T5: =S5/$S$24 -> 0.029918832 | U5: =T5*P5 -> 0.059837663 | V5: =S5*(1+Q5)^($P$18-P5) -> 2.9175311 | X5: =P5*(P5+1)*S5 -> 12.877118 | AA5: 2 | AB5: =AB4-$Q$2/2 -> 0.0214 | AC5: =$C$10 -> 2.25 | AD5: =AC5/(1+AB5)^AA5 -> 2.1567053 | AE5: =AD5/$AD$24 -> 0.014959676 | AF5: =AE5*AA5 -> 0.029919351 | AG5: =AD5*(1+AB5)^($P$18-AA5) -> 2.8401214 | AI5: =AA5*(AA5+1)*AD5 -> 12.940232
B6: Yield | C6: 0.0453 | E6: 3 | F6: =$C$7 -> 0.02265 | G6: =$C$10 -> 2.25 | H6: =G6/(1+F6)^E6 -> 2.1037855 | I6: =H6/$H$24 -> 0.021088279 | J6: =I6*E6 -> 0.063264838 | K6: =H6*(1+F6)^($E$19-E6) -> 2.8148337 | M6: =E6*(E6+1)*H6 -> 25.245426 | P6: 3 | Q6: =Q5+$Q$2/2 -> 0.02515 | R6: =$C$10 -> 2.25 | S6: =R6/(1+Q6)^P6 -> 2.0884317 | T6: =S6/$S$24 -> 0.029113704 | U6: =T6*P6 -> 0.087341113 | V6: =S6*(1+Q6)^($P$18-P6) -> 2.8136447 | X6: =P6*(P6+1)*S6 -> 25.06118 | AA6: 3 | AB6: =AB5-$Q$2/2 -> 0.02015 | AC6: =$C$10 -> 2.25 | AD6: =AC6/(1+AB6)^AA6 -> 2.1192901 | AE6: =AD6/$AD$24 -> 0.01470015 | AF6: =AE6*AA6 -> 0.044100451 | AG6: =AD6*(1+AB6)^($P$18-AA6) -> 2.6925193 | AI6: =AA6*(AA6+1)*AD6 -> 25.431482
B7: Semi-Annually Yield | C7: =C6/2 -> 0.02265 | E7: 4 | F7: =$C$7 -> 0.02265 | G7: =$C$10 -> 2.25 | H7: =G7/(1+F7)^E7 -> 2.0571901 | I7: =H7/$H$24 -> 0.020621209 | J7: =I7*E7 -> 0.082484836 | K7: =H7*(1+F7)^($E$19-E7) -> 2.6915267 | M7: =E7*(E7+1)*H7 -> 41.143802 | P7: 4 | Q7: =Q6+$Q$2/2 -> 0.0264 | R7: =$C$10 -> 2.25 | S7: =R7/(1+Q7)^P7 -> 2.0272903 | T7: =S7/$S$24 -> 0.028261366 | U7: =T7*P7 -> 0.11304546 | V7: =S7*(1+Q7)^($P$18-P7) -> 2.7002192 | X7: =P7*(P7+1)*S7 -> 40.545806 | AA7: 4 | AB7: =AB6-$Q$2/2 -> 0.0189 | AC7: =$C$10 -> 2.25 | AD7: =AC7/(1+AB7)^AA7 -> 2.0876432 | AE7: =AD7/$AD$24 -> 0.014480636 | AF7: =AE7*AA7 -> 0.057922543 | AG7: =AD7*(1+AB7)^($P$18-AA7) -> 2.565095 | AI7: =AA7*(AA7+1)*AD7 -> 41.752863
B8: Coupon Rate | C8: 0.045 | E8: 5 | F8: =$C$7 -> 0.02265 | G8: =$C$10 -> 2.25 | H8: =G8/(1+F8)^E8 -> 2.0116268 | I8: =H8/$H$24 -> 0.020164484 | J8: =I8*E8 -> 0.10082242 | K8: =H8*(1+F8)^($E$19-E8) -> 2.5736214 | M8: =E8*(E8+1)*H8 -> 60.348803 | P8: 5 | Q8: =Q7+$Q$2/2 -> 0.02765 | R8: =$C$10 -> 2.25 | S8: =R8/(1+Q8)^P8 -> 1.9631631 | T8: =S8/$S$24 -> 0.027367403 | U8: =T8*P8 -> 0.13683701 | V8: =S8*(1+Q8)^($P$18-P8) -> 2.5787465 | X8: =P8*(P8+1)*S8 -> 58.894893 | AA8: 5 | AB8: =AB7-$Q$2/2 -> 0.01765 | AC8: =$C$10 -> 2.25 | AD8: =AC8/(1+AB8)^AA8 -> 2.0615332 | AE8: =AD8/$AD$24 -> 0.014299528 | AF8: =AE8*AA8 -> 0.071497639 | AG8: =AD8*(1+AB8)^($P$18-AA8) -> 2.4556966 | AI8: =AA8*(AA8+1)*AD8 -> 61.845996
B9: Coupon | C9: =C5*C8 -> 4.5 | E9: 6 | F9: =$C$7 -> 0.02265 | G9: =$C$10 -> 2.25 | H9: =G9/(1+F9)^E9 -> 1.9670726 | I9: =H9/$H$24 -> 0.019717874 | J9: =I9*E9 -> 0.11830724 | K9: =H9*(1+F9)^($E$19-E9) -> 2.460881 | M9: =E9*(E9+1)*H9 -> 82.617048 | P9: 6 | Q9: =Q8+$Q$2/2 -> 0.0289 | R9: =$C$10 -> 2.25 | S9: =R9/(1+Q9)^P9 -> 1.8964592 | T9: =S9/$S$24 -> 0.02643752 | U9: =T9*P9 -> 0.15862512 | V9: =S9*(1+Q9)^($P$18-P9) -> 2.450767 | X9: =P9*(P9+1)*S9 -> 79.651288 | AA9: 6 | AB9: =AB8-$Q$2/2 -> 0.0164 | AC9: =$C$10 -> 2.25 | AD9: =AC9/(1+AB9)^AA9 -> 2.0407724 | AE9: =AD9/$AD$24 -> 0.014155524 | AF9: =AE9*AA9 -> 0.084933143 | AG9: =AD9*(1+AB9)^($P$18-AA9) -> 2.3625254 | AI9: =AA9*(AA9+1)*AD9 -> 85.712442
B10: Semi-Annually Coupon | C10: =C9/2 -> 2.25 | E10: 7 | F10: =$C$7 -> 0.02265 | G10: =$C$10 -> 2.25 | H10: =G10/(1+F10)^E10 -> 1.9235052 | I10: =H10/$H$24 -> 0.019281156 | J10: =I10*E10 -> 0.13496809 | K10: =H10*(1+F10)^($E$19-E10) -> 2.3530793 | M10: =E10*(E10+1)*H10 -> 107.71629 | P10: 7 | Q10: =Q9+$Q$2/2 -> 0.03015 | R10: =$C$10 -> 2.25 | S10: =R10/(1+Q10)^P10 -> 1.827592 | T10: =S10/$S$24 -> 0.025477479 | U10: =T10*P10 -> 0.17834235 | V10: =S10*(1+Q10)^($P$18-P10) -> 2.3178375 | X10: =P10*(P10+1)*S10 -> 102.34515 | AA10: 7 | AB10: =AB9-$Q$2/2 -> 0.01515 | AC10: =$C$10 -> 2.25 | AD10: =AC10/(1+AB10)^AA10 -> 2.0252143 | AE10: =AD10/$AD$24 -> 0.014047607 | AF10: =AE10*AA10 -> 0.098333249 | AG10: =AD10*(1+AB10)^($P$18-AA10) -> 2.2840875 | AI10: =AA10*(AA10+1)*AD10 -> 113.412
B11: Issue Date | C11: 45723 | E11: 8 | F11: =$C$7 -> 0.02265 | G11: =$C$10 -> 2.25 | H11: =G11/(1+F11)^E11 -> 1.8809027 | I11: =H11/$H$24 -> 0.01885411 | J11: =I11*E11 -> 0.15083288 | K11: =H11*(1+F11)^($E$19-E11) -> 2.25 | M11: =E11*(E11+1)*H11 -> 135.425 | P11: 8 | Q11: =Q10+$Q$2/2 -> 0.0314 | R11: =$C$10 -> 2.25 | S11: =R11/(1+Q11)^P11 -> 1.7569747 | T11: =S11/$S$24 -> 0.02449304 | U11: =T11*P11 -> 0.19594432 | V11: =S11*(1+Q11)^($P$18-P11) -> 2.1815009 | X11: =P11*(P11+1)*S11 -> 126.50218 | AA11: 8 | AB11: =AB10-$Q$2/2 -> 0.0139 | AC11: =$C$10 -> 2.25 | AD11: =AC11/(1+AB11)^AA11 -> 2.0147517 | AE11: =AD11/$AD$24 -> 0.013975035 | AF11: =AE11*AA11 -> 0.11180028 | AG11: =AD11*(1+AB11)^($P$18-AA11) -> 2.2191538 | AI11: =AA11*(AA11+1)*AD11 -> 145.06212
B12: Last Coupon Payment Date | C12: =EDATE(C11,6) -> 45907 | E12: 9 | F12: =$C$7 -> 0.02265 | G12: =$C$10 -> 2.25 | H12: =G12/(1+F12)^E12 -> 1.8392439 | I12: =H12/$H$24 -> 0.018436523 | J12: =I12*E12 -> 0.1659287 | K12: =H12*(1+F12)^($E$19-E12) -> 2.1514362 | M12: =E12*(E12+1)*H12 -> 165.53195 | P12: 9 | Q12: =Q11+$Q$2/2 -> 0.03265 | R12: =$C$10 -> 2.25 | S12: =R12/(1+Q12)^P12 -> 1.6850166 | T12: =S12/$S$24 -> 0.023489911 | U12: =T12*P12 -> 0.2114092 | V12: =S12*(1+Q12)^($P$18-P12) -> 2.0432574 | X12: =P12*(P12+1)*S12 -> 151.65149 | AA12: 9 | AB12: =AB11-$Q$2/2 -> 0.01265 | AC12: =$C$10 -> 2.25 | AD12: =AC12/(1+AB12)^AA12 -> 2.0093159 | AE12: =AD12/$AD$24 -> 0.01393733 | AF12: =AE12*AA12 -> 0.12543597 | AG12: =AD12*(1+AB12)^($P$18-AA12) -> 2.1667281 | AI12: =AA12*(AA12+1)*AD12 -> 180.83843
B13: Next Coupon Payment Date | C13: =EDATE(C12,6) -> 46088 | E13: 10 | F13: =$C$7 -> 0.02265 | G13: =$C$10 -> 2.25 | H13: =G13/(1+F13)^E13 -> 1.7985077 | I13: =H13/$H$24 -> 0.018028184 | J13: =I13*E13 -> 0.18028184 | K13: =H13*(1+F13)^($E$19-E13) -> 2.0571901 | M13: =E13*(E13+1)*H13 -> 197.83584 | P13: 10 | Q13: =Q12+$Q$2/2 -> 0.0339 | R13: =$C$10 -> 2.25 | S13: =R13/(1+Q13)^P13 -> 1.6121193 | T13: =S13/$S$24 -> 0.022473689 | U13: =T13*P13 -> 0.22473689 | V13: =S13*(1+Q13)^($P$18-P13) -> 1.9045389 | X13: =P13*(P13+1)*S13 -> 177.33312 | AA13: 10 | AB13: =AB12-$Q$2/2 -> 0.0114 | AC13: =$C$10 -> 2.25 | AD13: =AC13/(1+AB13)^AA13 -> 2.0088755 | AE13: =AD13/$AD$24 -> 0.013934275 | AF13: =AE13*AA13 -> 0.13934275 | AG13: =AD13*(1+AB13)^($P$18-AA13) -> 2.1260221 | AI13: =AA13*(AA13+1)*AD13 -> 220.97631
B14: Settlement Date | C14: 46005 | E14: 11 | F14: =$C$7 -> 0.02265 | G14: =$C$10 -> 2.25 | H14: =G14/(1+F14)^E14 -> 1.7586737 | I14: =H14/$H$24 -> 0.01762889 | J14: =I14*E14 -> 0.19391779 | K14: =H14*(1+F14)^($E$19-E14) -> 1.9670726 | M14: =E14*(E14+1)*H14 -> 232.14493 | P14: 11 | Q14: =Q13+$Q$2/2 -> 0.03515 | R14: =$C$10 -> 2.25 | S14: =R14/(1+Q14)^P14 -> 1.5386731 | T14: =S14/$S$24 -> 0.021449816 | U14: =T14*P14 -> 0.23594797 | V14: =S14*(1+Q14)^($P$18-P14) -> 1.7666866 | X14: =P14*(P14+1)*S14 -> 203.10485 | AA14: 11 | AB14: =AB13-$Q$2/2 -> 0.01015 | AC14: =$C$10 -> 2.25 | AD14: =AC14/(1+AB14)^AA14 -> 2.0134366 | AE14: =AD14/$AD$24 -> 0.013965913 | AF14: =AE14*AA14 -> 0.15362504 | AG14: =AD14*(1+AB14)^($P$18-AA14) -> 2.0964352 | AI14: =AA14*(AA14+1)*AD14 -> 265.77364
B15: Maturity Date | C15: 49375 | E15: 12 | F15: =$C$7 -> 0.02265 | G15: =$C$10 -> 2.25 | H15: =G15/(1+F15)^E15 -> 1.719722 | I15: =H15/$H$24 -> 0.017238439 | J15: =I15*E15 -> 0.20686127 | K15: =H15*(1+F15)^($E$19-E15) -> 1.8809027 | M15: =E15*(E15+1)*H15 -> 268.27663 | P15: 12 | Q15: =Q14+$Q$2/2 -> 0.0364 | R15: =$C$10 -> 2.25 | S15: =R15/(1+Q15)^P15 -> 1.4650541 | T15: =S15/$S$24 -> 0.020423533 | U15: =T15*P15 -> 0.24508239 | V15: =S15*(1+Q15)^($P$18-P15) -> 1.6309321 | X15: =P15*(P15+1)*S15 -> 228.54844 | AA15: 12 | AB15: =AB14-$Q$2/2 -> 0.0089 | AC15: =$C$10 -> 2.25 | AD15: =AC15/(1+AB15)^AA15 -> 2.0230427 | AE15: =AD15/$AD$24 -> 0.014032544 | AF15: =AE15*AA15 -> 0.16839053 | AG15: =AD15*(1+AB15)^($P$18-AA15) -> 2.0775401 | AI15: =AA15*(AA15+1)*AD15 -> 315.59466
E16: 13 | F16: =$C$7 -> 0.02265 | G16: =$C$10 -> 2.25 | H16: =G16/(1+F16)^E16 -> 1.681633 | I16: =H16/$H$24 -> 0.016856636 | J16: =I16*E16 -> 0.21913627 | K16: =H16*(1+F16)^($E$19-E16) -> 1.7985077 | M16: =E16*(E16+1)*H16 -> 306.05721 | P16: 13 | Q16: =Q15+$Q$2/2 -> 0.03765 | R16: =$C$10 -> 2.25 | S16: =R16/(1+Q16)^P16 -> 1.3916209 | T16: =S16/$S$24 -> 0.01939984 | U16: =T16*P16 -> 0.25219792 | V16: =S16*(1+Q16)^($P$18-P16) -> 1.4983826 | X16: =P16*(P16+1)*S16 -> 253.275 | AA16: 13 | AB16: =AB15-$Q$2/2 -> 0.00765 | AC16: =$C$10 -> 2.25 | AD16: =AC16/(1+AB16)^AA16 -> 2.0377753 | AE16: =AD16/$AD$24 -> 0.014134735 | AF16: =AE16*AA16 -> 0.18375155 | AG16: =AD16*(1+AB16)^($P$18-AA16) -> 2.0690725 | AI16: =AA16*(AA16+1)*AD16 -> 370.87511
E17: 14 | F17: =$C$7 -> 0.02265 | G17: =$C$10 -> 2.25 | H17: =G17/(1+F17)^E17 -> 1.6443876 | I17: =H17/$H$24 -> 0.01648329 | J17: =I17*E17 -> 0.23076606 | K17: =H17*(1+F17)^($E$19-E17) -> 1.719722 | M17: =E17*(E17+1)*H17 -> 345.3214 | P17: 14 | Q17: =Q16+$Q$2/2 -> 0.0389 | R17: =$C$10 -> 2.25 | S17: =R17/(1+Q17)^P17 -> 1.3187123 | T17: =S17/$S$24 -> 0.018383461 | U17: =T17*P17 -> 0.25736845 | V17: =S17*(1+Q17)^($P$18-P17) -> 1.3700103 | X17: =P17*(P17+1)*S17 -> 276.92959 | AA17: 14 | AB17: =AB16-$Q$2/2 -> 0.0064 | AC17: =$C$10 -> 2.25 | AD17: =AC17/(1+AB17)^AA17 -> 2.0577553 | AE17: =AD17/$AD$24 -> 0.014273323 | AF17: =AE17*AA17 -> 0.19982652 | AG17: =AD17*(1+AB17)^($P$18-AA17) -> 2.0709249 | AI17: =AA17*(AA17+1)*AD17 -> 432.12861
E18: 15 | F18: =$C$7 -> 0.02265 | G18: =$C$10 -> 2.25 | H18: =G18/(1+F18)^E18 -> 1.6079672 | I18: =H18/$H$24 -> 0.016118212 | J18: =I18*E18 -> 0.24177319 | K18: =H18*(1+F18)^($E$19-E18) -> 1.6443876 | M18: =E18*(E18+1)*H18 -> 385.91212 | P18: 15 | Q18: =Q17+$Q$2/2 -> 0.04015 | R18: =$C$10 -> 2.25 | S18: =R18/(1+Q18)^P18 -> 1.2466453 | T18: =S18/$S$24 -> 0.017378813 | U18: =T18*P18 -> 0.2606822 | V18: =S18*(1+Q18)^($P$18-P18) -> 1.2466453 | X18: =P18*(P18+1)*S18 -> 299.19488 | AA18: 15 | AB18: =AB17-$Q$2/2 -> 0.00515 | AC18: =$C$10 -> 2.25 | AD18: =AC18/(1+AB18)^AA18 -> 2.0831443 | AE18: =AD18/$AD$24 -> 0.01444943 | AF18: =AE18*AA18 -> 0.21674146 | AG18: =AD18*(1+AB18)^($P$18-AA18) -> 2.0831443 | AI18: =AA18*(AA18+1)*AD18 -> 499.95464
E19: 16 | F19: =$C$7 -> 0.02265 | G19: =$C$10 -> 2.25 | H19: =G19/(1+F19)^E19 -> 1.5723534 | I19: =H19/$H$24 -> 0.015761221 | J19: =I19*E19 -> 0.25217953 | K19: =H19*(1+F19)^($E$19-E19) -> 1.5723534 | M19: =E19*(E19+1)*H19 -> 427.68012 | P19: 16 | Q19: =Q18+$Q$2/2 -> 0.0414 | R19: =$C$10 -> 2.25 | S19: =R19/(1+Q19)^P19 -> 1.1757131 | T19: =S19/$S$24 -> 0.016389984 | U19: =T19*P19 -> 0.26223975 | W19: =SUM(V4:V18) -> 32.431167 | X19: =P19*(P19+1)*S19 -> 319.79395 | AA19: 16 | AB19: =AB18-$Q$2/2 -> 0.0039 | AC19: =$C$10 -> 2.25 | AD19: =AC19/(1+AB19)^AA19 -> 2.1141473 | AE19: =AD19/$AD$24 -> 0.014664478 | AF19: =AE19*AA19 -> 0.23463165 | AG19: =AD19*(1+AB19)^($P$18-AA19) -> 2.1059342 | AI19: =AA19*(AA19+1)*AD19 -> 575.04808
E20: 17 | F20: =$C$7 -> 0.02265 | G20: =$C$10 -> 2.25 | H20: =G20/(1+F20)^E20 -> 1.5375284 | I20: =H20/$H$24 -> 0.015412136 | J20: =I20*E20 -> 0.26200631 | L20: =SUM(K4:K19) -> 35.957958 | M20: =E20*(E20+1)*H20 -> 470.48368 | P20: 17 | Q20: =Q19+$Q$2/2 -> 0.04265 | R20: =$C$10 -> 2.25 | S20: =R20/(1+Q20)^P20 -> 1.1061836 | T20: =S20/$S$24 -> 0.015420711 | U20: =T20*P20 -> 0.26215209 | X20: =P20*(P20+1)*S20 -> 338.49218 | AA20: 17 | AB20: =AB19-$Q$2/2 -> 0.00265 | AC20: =$C$10 -> 2.25 | AD20: =AC20/(1+AB20)^AA20 -> 2.151015 | AE20: =AD20/$AD$24 -> 0.014920205 | AF20: =AE20*AA20 -> 0.25364349 | AH20: =SUM(AG4:AG18) -> 35.119533 | AI20: =AA20*(AA20+1)*AD20 -> 658.21058
E21: 18 | F21: =$C$7 -> 0.02265 | G21: =$C$10 -> 2.25 | H21: =G21/(1+F21)^E21 -> 1.5034746 | I21: =H21/$H$24 -> 0.015070783 | J21: =I21*E21 -> 0.27127409 | M21: =E21*(E21+1)*H21 -> 514.18833 | P21: 18 | Q21: =Q20+$Q$2/2 -> 0.0439 | R21: =$C$10 -> 2.25 | S21: =R21/(1+Q21)^P21 -> 1.0382988 | T21: =S21/$S$24 -> 0.014474366 | U21: =T21*P21 -> 0.26053859 | X21: =P21*(P21+1)*S21 -> 355.0982 | AA21: 18 | AB21: =AB20-$Q$2/2 -> 0.0014 | AC21: =$C$10 -> 2.25 | AD21: =AC21/(1+AB21)^AA21 -> 2.1940471 | AE21: =AD21/$AD$24 -> 0.015218692 | AF21: =AE21*AA21 -> 0.27393645 | AI21: =AA21*(AA21+1)*AD21 -> 750.36412
E22: 19 | F22: =$C$7 -> 0.02265 | G22: =$C$10 -> 2.25 | H22: =G22/(1+F22)^E22 -> 1.4701752 | I22: =H22/$H$24 -> 0.01473699 | J22: =I22*E22 -> 0.28000281 | M22: =E22*(E22+1)*H22 -> 558.66657 | P22: 19 | Q22: =Q21+$Q$2/2 -> 0.04515 | R22: =$C$10 -> 2.25 | S22: =R22/(1+Q22)^P22 -> 0.97227394 | T22: =S22/$S$24 -> 0.013553949 | U22: =T22*P22 -> 0.25752503 | X22: =P22*(P22+1)*S22 -> 369.4641 | AA22: 19 | AB22: =AB21-$Q$2/2 -> 0.00015 | AC22: =$C$10 -> 2.25 | AD22: =AC22/(1+AB22)^AA22 -> 2.2435971 | AE22: =AD22/$AD$24 -> 0.015562388 | AF22: =AE22*AA22 -> 0.29568537 | AI22: =AA22*(AA22+1)*AD22 -> 852.5669
E23: 20 | F23: =$C$7 -> 0.02265 | G23: =$C$10+$C$5 -> 102.25 | H23: =G23/(1+F23)^E23 -> 65.331535 | I23: =H23/$H$24 -> 0.65488126 | J23: =I23*E23 -> 13.097625 | M23: =E23*(E23+1)*H23 -> 27439.245 | P23: 20 | Q23: =Q22+$Q$2/2 -> 0.0464 | R23: =$C$10+$C$5 -> 102.25 | S23: =R23/(1+Q23)^P23 -> 41.277054 | T23: =S23/$S$24 -> 0.57542125 | U23: =T23*P23 -> 11.508425 | X23: =P23*(P23+1)*S23 -> 17336.363 | AA23: 20 | AB23: =AB22-$Q$2/2 -> -0.0011 | AC23: =$C$10+$C$5 -> 102.25 | AD23: =AC23/(1+AB23)^AA23 -> 104.52569 | AE23: =AD23/$AD$24 -> 0.7250274 | AF23: =AE23*AA23 -> 14.500548 | AI23: =AA23*(AA23+1)*AD23 -> 43900.791
H24: =SUM(H4:H23) -> 99.760887 | J24: =SUM(J4:J23) -> 16.31762 | M24: =SUM(M4:M23) -> 31781.149 | S24: =SUM(S4:S23) -> 71.733629 | U24: =SUM(U4:U23) -> 15.19895 | X24: =SUM(X4:X23) -> 20759.527 | AD24: =SUM(AD4:AD23) -> 144.16792 | AF24: =SUM(AF4:AF23) -> 17.259326 | AI24: =SUM(AI4:AI23) -> 49513.679
E26: Macaulay Duration | F26: =J24 -> 16.31762 | P26: Macaulay Duration | Q26: =U24 -> 15.19895 | AA26: Macaulay Duration | AB26: =AF24 -> 17.259326
E27: Modified Duration | F27: =F26/(1+$C$6) -> 15.610465 | P27: Modified Duration | Q27: =Q26/(1+$C$6) -> 14.540275 | AA27: Modified Duration | AB27: =AB26/(1+$C$6) -> 16.511362
E28: Convexity | F28: =M24/H24 -> 318.57324 | P28: Convexity | Q28: =X24/S24 -> 289.39741 | AA28: Convexity | AB28: =AI24/AD24 -> 343.4445
E29: GBP01 | F29: =H24*F27*0.0001 -> 0.15573139 | P29: GBP01 | Q29: =S24*Q27*0.0001 -> 0.10430267 | AA29: GBP01 | AB29: =AD24*AB27*0.0001 -> 0.23804087

Sheet 30 year Gilt
B2: 30-Year Bond | F2: Coupon Payment Date | G2: Period | H2: Cash Flow | I2: PV of CF | J2: PV as % of Sum of PV | K2: TW PV of CF | L2: TW^2 PV of CF | O2: Yield | P2: Price | Q2: Duration Implied Price | R2: Convexity Implied Price
B3: Price | C3: =I62 -> 86.694441 | F3: =C10 -> 45869 | O3: 0.01 | P3: 152.07025 | Q3: =$I$62*(1-$C$18*(O3-$C$5)) -> 197.68049 | R3: =$I$62*(1-$C$18*(O3-$C$5)+0.5*$C$19*((O3-$C$5)^2)) -> 312.73773
B4: Face Value | C4: 100 | F4: =EDATE(F3,6) -> 46053 | G4: 1 | H4: =$C$9 -> 2.1875 | I4: =H4/(1+$C$6)^G4 -> 2.1312769 | J4: =I4/$I$62 -> 0.024583778 | K4: =J4*G4 -> 0.024583778 | L4: =G4*(G4+1)*I4 -> 4.2625538 | O4: 0.015 | P4: 126.50693 | Q4: =$I$62*(1-$C$18*(O4-$C$5)) -> 184.7027 | R4: =$I$62*(1-$C$18*(O4-$C$5)+0.5*$C$19*((O4-$C$5)^2)) -> 274.42544
B5: Yield | C5: 0.05276 | F5: =EDATE(F4,6) -> 46234 | G5: 2 | H5: =$C$9 -> 2.1875 | I5: =H5/(1+$C$6)^G5 -> 2.0764989 | J5: =I5/$I$62 -> 0.023951926 | K5: =J5*G5 -> 0.047903853 | L5: =G5*(G5+1)*I5 -> 12.458993 | O5: 0.02 | P5: 106.40223 | Q5: =$I$62*(1-$C$18*(O5-$C$5)) -> 171.72491 | R5: =$I$62*(1-$C$18*(O5-$C$5)+0.5*$C$19*((O5-$C$5)^2)) -> 239.25952
B6: Semi-Annually Yield | C6: =C5/2 -> 0.02638 | F6: =EDATE(F5,6) -> 46418 | G6: 3 | H6: =$C$9 -> 2.1875 | I6: =H6/(1+$C$6)^G6 -> 2.0231287 | J6: =I6/$I$62 -> 0.023336314 | K6: =J6*G6 -> 0.070008943 | L6: =G6*(G6+1)*I6 -> 24.277545 | O6: 0.025 | P6: 90.484873 | Q6: =$I$62*(1-$C$18*(O6-$C$5)) -> 158.74713 | R6: =$I$62*(1-$C$18*(O6-$C$5)+0.5*$C$19*((O6-$C$5)^2)) -> 207.23995
B7: Coupon Rate | C7: 0.04375 | F7: =EDATE(F6,6) -> 46599 | G7: 4 | H7: =$C$9 -> 2.1875 | I7: =H7/(1+$C$6)^G7 -> 1.9711303 | J7: =I7/$I$62 -> 0.022736525 | K7: =J7*G7 -> 0.090946099 | L7: =G7*(G7+1)*I7 -> 39.422606 | O7: 0.03 | P7: 77.793558 | Q7: =$I$62*(1-$C$18*(O7-$C$5)) -> 145.76934 | R7: =$I$62*(1-$C$18*(O7-$C$5)+0.5*$C$19*((O7-$C$5)^2)) -> 178.36675
B8: Coupon | C8: =C4*C7 -> 4.375 | F8: =EDATE(F7,6) -> 46783 | G8: 5 | H8: =$C$9 -> 2.1875 | I8: =H8/(1+$C$6)^G8 -> 1.9204684 | J8: =I8/$I$62 -> 0.022152151 | K8: =J8*G8 -> 0.11076076 | L8: =G8*(G8+1)*I8 -> 57.614051 | O8: 0.035 | P8: 67.59907 | Q8: =$I$62*(1-$C$18*(O8-$C$5)) -> 132.79155 | R8: =$I$62*(1-$C$18*(O8-$C$5)+0.5*$C$19*((O8-$C$5)^2)) -> 152.6399
B9: Semi-Annually Coupon | C9: =C8/2 -> 2.1875 | F9: =EDATE(F8,6) -> 46965 | G9: 6 | H9: =$C$9 -> 2.1875 | I9: =H9/(1+$C$6)^G9 -> 1.8711085 | J9: =I9/$I$62 -> 0.021582797 | K9: =J9*G9 -> 0.12949678 | L9: =G9*(G9+1)*I9 -> 78.586558 | O9: 0.04 | P9: 59.34641 | Q9: =$I$62*(1-$C$18*(O9-$C$5)) -> 119.81376 | R9: =$I$62*(1-$C$18*(O9-$C$5)+0.5*$C$19*((O9-$C$5)^2)) -> 130.05942
B10: Issue Date | C10: 45869 | F10: =EDATE(F9,6) -> 47149 | G10: 7 | H10: =$C$9 -> 2.1875 | I10: =H10/(1+$C$6)^G10 -> 1.8230173 | J10: =I10/$I$62 -> 0.021028076 | K10: =J10*G10 -> 0.14719653 | L10: =G10*(G10+1)*I10 -> 102.08897 | O10: 0.045 | P10: 52.611704 | Q10: =$I$62*(1-$C$18*(O10-$C$5)) -> 106.83597 | R10: =$I$62*(1-$C$18*(O10-$C$5)+0.5*$C$19*((O10-$C$5)^2)) -> 110.6253
B11: Last Coupon Payment Date | C11: =C10 -> 45869 | F11: =EDATE(F10,6) -> 47330 | G11: 8 | H11: =$C$9 -> 2.1875 | I11: =H11/(1+$C$6)^G11 -> 1.7761622 | J11: =I11/$I$62 -> 0.020487613 | K11: =J11*G11 -> 0.1639009 | L11: =G11*(G11+1)*I11 -> 127.88368 | O11: 0.05 | P11: 47.070039 | Q11: =$I$62*(1-$C$18*(O11-$C$5)) -> 93.858181 | R11: =$I$62*(1-$C$18*(O11-$C$5)+0.5*$C$19*((O11-$C$5)^2)) -> 94.337535
B12: Next Coupon Payment Date | C12: =EDATE(C11,6) -> 46053 | F12: =EDATE(F11,6) -> 47514 | G12: 9 | H12: =$C$9 -> 2.1875 | I12: =H12/(1+$C$6)^G12 -> 1.7305113 | J12: =I12/$I$62 -> 0.019961041 | K12: =J12*G12 -> 0.17964937 | L12: =G12*(G12+1)*I12 -> 155.74602 | O12: 0.055 | P12: 42.471402 | Q12: =$I$62*(1-$C$18*(O12-$C$5)) -> 80.880392 | R12: =$I$62*(1-$C$18*(O12-$C$5)+0.5*$C$19*((O12-$C$5)^2)) -> 81.196136
B13: Settlement Date | C13: 46005 | F13: =EDATE(F12,6) -> 47695 | G13: 10 | H13: =$C$9 -> 2.1875 | I13: =H13/(1+$C$6)^G13 -> 1.6860337 | J13: =I13/$I$62 -> 0.019448002 | K13: =J13*G13 -> 0.19448002 | L13: =G13*(G13+1)*I13 -> 185.46371 | O13: 0.06 | P13: 38.622638 | Q13: =$I$62*(1-$C$18*(O13-$C$5)) -> 67.902603 | R13: =$I$62*(1-$C$18*(O13-$C$5)+0.5*$C$19*((O13-$C$5)^2)) -> 71.201097
B14: Maturity Date | C14: 56461 | F14: =EDATE(F13,6) -> 47879 | G14: 11 | H14: =$C$9 -> 2.1875 | I14: =H14/(1+$C$6)^G14 -> 1.6426993 | J14: =I14/$I$62 -> 0.01894815 | K14: =J14*G14 -> 0.20842965 | L14: =G14*(G14+1)*I14 -> 216.83631 | O14: 0.065 | P14: 35.373886 | Q14: =$I$62*(1-$C$18*(O14-$C$5)) -> 54.924814 | R14: =$I$62*(1-$C$18*(O14-$C$5)+0.5*$C$19*((O14-$C$5)^2)) -> 64.35242
F15: =EDATE(F14,6) -> 48060 | G15: 12 | H15: =$C$9 -> 2.1875 | I15: =H15/(1+$C$6)^G15 -> 1.6004787 | J15: =I15/$I$62 -> 0.018461145 | K15: =J15*G15 -> 0.22153374 | L15: =G15*(G15+1)*I15 -> 249.67467 | O15: 0.07 | P15: 32.608356 | Q15: =$I$62*(1-$C$18*(O15-$C$5)) -> 41.947025 | R15: =$I$62*(1-$C$18*(O15-$C$5)+0.5*$C$19*((O15-$C$5)^2)) -> 60.650103
F16: =EDATE(F15,6) -> 48244 | G16: 13 | H16: =$C$9 -> 2.1875 | I16: =H16/(1+$C$6)^G16 -> 1.5593432 | J16: =I16/$I$62 -> 0.017986657 | K16: =J16*G16 -> 0.23382654 | L16: =G16*(G16+1)*I16 -> 283.80046 | O16: 0.075 | P16: 30.234606 | Q16: =$I$62*(1-$C$18*(O16-$C$5)) -> 28.969236 | R16: =$I$62*(1-$C$18*(O16-$C$5)+0.5*$C$19*((O16-$C$5)^2)) -> 60.094148
B17: Macaulay Duration | C17: =K62 -> 31.518738 | F17: =EDATE(F16,6) -> 48426 | G17: 14 | H17: =$C$9 -> 2.1875 | I17: =H17/(1+$C$6)^G17 -> 1.519265 | J17: =I17/$I$62 -> 0.017524364 | K17: =J17*G17 -> 0.2453411 | L17: =G17*(G17+1)*I17 -> 319.04565 | O17: 0.08 | P17: 28.180692 | Q17: =$I$62*(1-$C$18*(O17-$C$5)) -> 15.991447 | R17: =$I$62*(1-$C$18*(O17-$C$5)+0.5*$C$19*((O17-$C$5)^2)) -> 62.684554
B18: Modified Duration | C18: =C17/(1+C5) -> 29.939149 | F18: =EDATE(F17,6) -> 48610 | G18: 15 | H18: =$C$9 -> 2.1875 | I18: =H18/(1+$C$6)^G18 -> 1.4802169 | J18: =I18/$I$62 -> 0.017073954 | K18: =J18*G18 -> 0.2561093 | L18: =G18*(G18+1)*I18 -> 355.25205
B19: Convexity | C19: =L62/I62 -> 1451.7014 | F19: =EDATE(F18,6) -> 48791 | G19: 16 | H19: =$C$9 -> 2.1875 | I19: =H19/(1+$C$6)^G19 -> 1.4421724 | J19: =I19/$I$62 -> 0.016635119 | K19: =J19*G19 -> 0.26616191 | L19: =G19*(G19+1)*I19 -> 392.27088
F20: =EDATE(F19,6) -> 48975 | G20: 17 | H20: =$C$9 -> 2.1875 | I20: =H20/(1+$C$6)^G20 -> 1.4051057 | J20: =I20/$I$62 -> 0.016207564 | K20: =J20*G20 -> 0.27552858 | L20: =G20*(G20+1)*I20 -> 429.96234
F21: =EDATE(F20,6) -> 49156 | G21: 18 | H21: =$C$9 -> 2.1875 | I21: =H21/(1+$C$6)^G21 -> 1.3689917 | J21: =I21/$I$62 -> 0.015790997 | K21: =J21*G21 -> 0.28423795 | L21: =G21*(G21+1)*I21 -> 468.19515
F22: =EDATE(F21,6) -> 49340 | G22: 19 | H22: =$C$9 -> 2.1875 | I22: =H22/(1+$C$6)^G22 -> 1.3338059 | J22: =I22/$I$62 -> 0.015385137 | K22: =J22*G22 -> 0.29231761 | L22: =G22*(G22+1)*I22 -> 506.84623
F23: =EDATE(F22,6) -> 49521 | G23: 20 | H23: =$C$9 -> 2.1875 | I23: =H23/(1+$C$6)^G23 -> 1.2995244 | J23: =I23/$I$62 -> 0.014989709 | K23: =J23*G23 -> 0.29979417 | L23: =G23*(G23+1)*I23 -> 545.80026
F24: =EDATE(F23,6) -> 49705 | G24: 21 | H24: =$C$9 -> 2.1875 | I24: =H24/(1+$C$6)^G24 -> 1.2661241 | J24: =I24/$I$62 -> 0.014604443 | K24: =J24*G24 -> 0.30669331 | L24: =G24*(G24+1)*I24 -> 584.94932
F25: =EDATE(F24,6) -> 49887 | G25: 22 | H25: =$C$9 -> 2.1875 | I25: =H25/(1+$C$6)^G25 -> 1.2335822 | J25: =I25/$I$62 -> 0.01422908 | K25: =J25*G25 -> 0.31303977 | L25: =G25*(G25+1)*I25 -> 624.19258
F26: =EDATE(F25,6) -> 50071 | G26: 23 | H26: =$C$9 -> 2.1875 | I26: =H26/(1+$C$6)^G26 -> 1.2018767 | J26: =I26/$I$62 -> 0.013863365 | K26: =J26*G26 -> 0.31885739 | L26: =G26*(G26+1)*I26 -> 663.43592
F27: =EDATE(F26,6) -> 50252 | G27: 24 | H27: =$C$9 -> 2.1875 | I27: =H27/(1+$C$6)^G27 -> 1.1709861 | J27: =I27/$I$62 -> 0.013507049 | K27: =J27*G27 -> 0.32416917 | L27: =G27*(G27+1)*I27 -> 702.59163
F28: =EDATE(F27,6) -> 50436 | G28: 25 | H28: =$C$9 -> 2.1875 | I28: =H28/(1+$C$6)^G28 -> 1.1408894 | J28: =I28/$I$62 -> 0.013159891 | K28: =J28*G28 -> 0.32899727 | L28: =G28*(G28+1)*I28 -> 741.5781
F29: =EDATE(F28,6) -> 50617 | G29: 26 | H29: =$C$9 -> 2.1875 | I29: =H29/(1+$C$6)^G29 -> 1.1115663 | J29: =I29/$I$62 -> 0.012821656 | K29: =J29*G29 -> 0.33336305 | L29: =G29*(G29+1)*I29 -> 780.31952
F30: =EDATE(F29,6) -> 50801 | G30: 27 | H30: =$C$9 -> 2.1875 | I30: =H30/(1+$C$6)^G30 -> 1.0829968 | J30: =I30/$I$62 -> 0.012492114 | K30: =J30*G30 -> 0.33728707 | L30: =G30*(G30+1)*I30 -> 818.74559
F31: =EDATE(F30,6) -> 50982 | G31: 28 | H31: =$C$9 -> 2.1875 | I31: =H31/(1+$C$6)^G31 -> 1.0551617 | J31: =I31/$I$62 -> 0.012171042 | K31: =J31*G31 -> 0.34078916 | L31: =G31*(G31+1)*I31 -> 856.79126
... F60: =EDATE(F59,6) -> 56280 | G60: 57 | H60: =$C$9 -> 2.1875 | I60: =H60/(1+$C$6)^G60 -> 0.4958859 | J60: =I60/$I$62 -> 0.0057199272 | K60: =J60*G60 -> 0.32603585 | L60: =G60*(G60+1)*I60 -> 1639.3988
F61: =EDATE(F60,6) -> 56461 | G61: 58 | H61: =$C$9+C4 -> 102.1875 | I61: =H61/(1+$C$6)^G61 -> 22.56957 | J61: =I61/$I$62 -> 0.26033469 | K61: =J61*G61 -> 15.099412 | L61: =G61*(G61+1)*I61 -> 77233.069
I62: =SUM(I4:I61) -> 86.694441 | K62: =SUM(K4:K61) -> 31.518738 | L62: =SUM(L4:L61) -> 125854.44

Sheet 30 Year Scenario
P2: Parallel Up | Q2: 0.0025 | AA2: Parallel Down | AB2: 0.0025
B3: 30-Year Bond | E3: Period | F3: Scenario Rate | G3: Cash Flow | H3: PV of CF | I3: PV as % of CF | J3: TW PV of CF | K3: Reivestment as per theory | M3: TW^2 PV of CF | P3: Period | Q3: Scenario Rate | R3: Cash Flow | S3: PV of CF | T3: PV as % of CF | U3: TW PV of CF | V3: Reivestment as per theory | X3: TW^2 PV of CF | AA3: Period | AB3: Scenario Rate | AC3: Cash Flow | AD3: PV of CF | AE3: PV as % of CF | AF3: TW PV of CF | AG3: Reivestment as per theory | AI3: TW^2 PV of CF
B4: Price | C4: 86.767 | E4: 1 | F4: =$C$7 -> 0.02638 | G4: =$C$10 -> 2.1875 | H4: =G4/(1+F4)^E4 -> 2.1312769 | I4: =H4/H$64 -> 0.024638171 | J4: =I4*E4 -> 0.024638171 | K4: =H4*(1+F4)^(E$35-E4) -> 4.7774207 | M4: =E4*(E4+1)*H4 -> 4.2625538 | P4: 1 | Q4: =$C$7 + INT((ROW()-4)/5)*$Q$2 -> 0.02638 | R4: =$C$10 -> 2.1875 | S4: =R4/(1+Q4)^P4 -> 2.1312769 | T4: =S4/S$64 -> 0.039449205 | U4: =T4*P4 -> 0.039449205 | V4: =S4*(1+Q4)^(P$35-P4) -> 4.7774207 | X4: =P4*(P4+1)*S4 -> 4.2625538 | AA4: 1 | AB4: =$C$7 + INT((ROW()-4)/5)*(-$Q$2) -> 0.02638 | AC4: =$C$10 -> 2.1875 | AD4: =AC4/(1+AB4)^AA4 -> 2.1312769 | AE4: =AD4/AD$64 -> 0.010061817 | AF4: =AE4*AA4 -> 0.010061817 | AG4: =AD4*(1+AB4)^(AA$35-AA4) -> 4.7774207 | AI4: =AA4*(AA4+1)*AD4 -> 4.2625538
B5: Face Value | C5: 100 | E5: 2 | F5: =$C$7 -> 0.02638 | G5: =$C$10 -> 2.1875 | H5: =G5/(1+F5)^E5 -> 2.0764989 | I5: =H5/H$64 -> 0.024004921 | J5: =I5*E5 -> 0.048009842 | K5: =H5*(1+F5)^(E$35-E5) -> 4.5349983 | M5: =E5*(E5+1)*H5 -> 12.458993 | P5: 2 | Q5: =$C$7 + INT((ROW()-4)/5)*$Q$2 -> 0.02638 | R5: =$C$10 -> 2.1875 | S5: =R5/(1+Q5)^P5 -> 2.0764989 | T5: =S5/S$64 -> 0.038435283 | U5: =T5*P5 -> 0.076870565 | V5: =S5*(1+Q5)^(P$35-P5) -> 4.5349983 | X5: =P5*(P5+1)*S5 -> 12.458993 | AA5: 2 | AB5: =$C$7 + INT((ROW()-4)/5)*(-$Q$2) -> 0.02638 | AC5: =$C$10 -> 2.1875 | AD5: =AC5/(1+AB5)^AA5 -> 2.0764989 | AE5: =AD5/AD$64 -> 0.0098032086 | AF5: =AE5*AA5 -> 0.019606417 | AG5: =AD5*(1+AB5)^(AA$35-AA5) -> 4.5349983 | AI5: =AA5*(AA5+1)*AD5 -> 12.458993
B6: Yield | C6: 0.05276 | E6: 3 | F6: =$C$7 -> 0.02638 | G6: =$C$10 -> 2.1875 | H6: =G6/(1+F6)^E6 -> 2.0231287 | I6: =H6/H$64 -> 0.023387947 | J6: =I6*E6 -> 0.070163841 | K6: =H6*(1+F6)^(E$35-E6) -> 4.3048772 | M6: =E6*(E6+1)*H6 -> 24.277545 | P6: 3 | Q6: =$C$7 + INT((ROW()-4)/5)*$Q$2 -> 0.02638 | R6: =$C$10 -> 2.1875 | S6: =R6/(1+Q6)^P6 -> 2.0231287 | T6: =S6/S$64 -> 0.03744742 | U6: =T6*P6 -> 0.11234226 | V6: =S6*(1+Q6)^(P$35-P6) -> 4.3048772 | X6: =P6*(P6+1)*S6 -> 24.277545 | AA6: 3 | AB6: =$C$7 + INT((ROW()-4)/5)*(-$Q$2) -> 0.02638 | AC6: =$C$10 -> 2.1875 | AD6: =AC6/(1+AB6)^AA6 -> 2.0231287 | AE6: =AD6/AD$64 -> 0.0095512468 | AF6: =AE6*AA6 -> 0.02865374 | AG6: =AD6*(1+AB6)^(AA$35-AA6) -> 4.3048772 | AI6: =AA6*(AA6+1)*AD6 -> 24.277545
B7: Semi-Annually Yield | C7: =C6/2 -> 0.02638 | E7: 4 | F7: =$C$7 -> 0.02638 | G7: =$C$10 -> 2.1875 | H7: =G7/(1+F7)^E7 -> 1.9711303 | I7: =H7/H$64 -> 0.022786831 | J7: =I7*E7 -> 0.091147322 | K7: =H7*(1+F7)^(E$35-E7) -> 4.0864332 | M7: =E7*(E7+1)*H7 -> 39.422606 | P7: 4 | Q7: =$C$7 + INT((ROW()-4)/5)*$Q$2 -> 0.02638 | R7: =$C$10 -> 2.1875 | S7: =R7/(1+Q7)^P7 -> 1.9711303 | T7: =S7/S$64 -> 0.036484947 | U7: =T7*P7 -> 0.14593979 | V7: =S7*(1+Q7)^(P$35-P7) -> 4.0864332 | X7: =P7*(P7+1)*S7 -> 39.422606 | AA7: 4 | AB7: =$C$7 + INT((ROW()-4)/5)*(-$Q$2) -> 0.02638 | AC7: =$C$10 -> 2.1875 | AD7: =AC7/(1+AB7)^AA7 -> 1.9711303 | AE7: =AD7/AD$64 -> 0.0093057608 | AF7: =AE7*AA7 -> 0.037223043 | AG7: =AD7*(1+AB7)^(AA$35-AA7) -> 4.0864332 | AI7: =AA7*(AA7+1)*AD7 -> 39.422606
B8: Coupon Rate | C8: 0.04375 | E8: 5 | F8: =$C$7 -> 0.02638 | G8: =$C$10 -> 2.1875 | H8: =G8/(1+F8)^E8 -> 1.9204684 | I8: =H8/H$64 -> 0.022201164 | J8: =I8*E8 -> 0.11100582 | K8: =H8*(1+F8)^(E$35-E8) -> 3.8790738 | M8: =E8*(E8+1)*H8 -> 57.614051 | P8: 5 | Q8: =$C$7 + INT((ROW()-4)/5)*$Q$2 -> 0.02638 | R8: =$C$10 -> 2.1875 | S8: =R8/(1+Q8)^P8 -> 1.9204684 | T8: =S8/S$64 -> 0.035547211 | U8: =T8*P8 -> 0.17773606 | V8: =S8*(1+Q8)^(P$35-P8) -> 3.8790738 | X8: =P8*(P8+1)*S8 -> 57.614051 | AA8: 5 | AB8: =$C$7 + INT((ROW()-4)/5)*(-$Q$2) -> 0.02638 | AC8: =$C$10 -> 2.1875 | AD8: =AC8/(1+AB8)^AA8 -> 1.9204684 | AE8: =AD8/AD$64 -> 0.0090665843 | AF8: =AE8*AA8 -> 0.045332921 | AG8: =AD8*(1+AB8)^(AA$35-AA8) -> 3.8790738 | AI8: =AA8*(AA8+1)*AD8 -> 57.614051
B9: Coupon | C9: =C5*C8 -> 4.375 | E9: 6 | F9: =$C$7 -> 0.02638 | G9: =$C$10 -> 2.1875 | H9: =G9/(1+F9)^E9 -> 1.8711085 | I9: =H9/H$64 -> 0.02163055 | J9: =I9*E9 -> 0.1297833 | K9: =H9*(1+F9)^(E$35-E9) -> 3.6822365 | M9: =E9*(E9+1)*H9 -> 78.586558 | P9: 6 | Q9: =$C$7 + INT((ROW()-4)/5)*$Q$2 -> 0.02888 | R9: =$C$10 -> 2.1875 | S9: =R9/(1+Q9)^P9 -> 1.8439949 | T9: =S9/S$64 -> 0.034131713 | U9: =T9*P9 -> 0.20479028 | V9: =S9*(1+Q9)^(P$35-P9) -> 3.8658283 | X9: =P9*(P9+1)*S9 -> 77.447785 | AA9: 6 | AB9: =$C$7 + INT((ROW()-4)/5)*(-$Q$2) -> 0.02388 | AC9: =$C$10 -> 2.1875 | AD9: =AC9/(1+AB9)^AA9 -> 1.8986884 | AE9: =AD9/AD$64 -> 0.0089637606 | AF9: =AE9*AA9 -> 0.053782564 | AG9: =AD9*(1+AB9)^(AA$35-AA9) -> 3.5069474 | AI9: =AA9*(AA9+1)*AD9 -> 79.744914
B10: Semi-Annually Coupon | C10: =C9/2 -> 2.1875 | E10: 7 | F10: =$C$7 -> 0.02638 | G10: =$C$10 -> 2.1875 | H10: =G10/(1+F10)^E10 -> 1.8230173 | I10: =H10/H$64 -> 0.021074602 | J10: =I10*E10 -> 0.14752221 | K10: =H10*(1+F10)^(E$35-E10) -> 3.4953874 | M10: =E10*(E10+1)*H10 -> 102.08897 | P10: 7 | Q10: =$C$7 + INT((ROW()-4)/5)*$Q$2 -> 0.02888 | R10: =$C$10 -> 2.1875 | S10: =R10/(1+Q10)^P10 -> 1.7922351 | T10: =S10/S$64 -> 0.033173658 | U10: =T10*P10 -> 0.23221561 | V10: =S10*(1+Q10)^(P$35-P10) -> 3.6518516 | X10: =P10*(P10+1)*S10 -> 100.36517 | AA10: 7 | AB10: =$C$7 + INT((ROW()-4)/5)*(-$Q$2) -> 0.02388 | AC10: =$C$10 -> 2.1875 | AD10: =AC10/(1+AB10)^AA10 -> 1.8544052 | AE10: =AD10/AD$64 -> 0.0087546984 | AF10: =AE10*AA10 -> 0.061282889 | AG10: =AD10*(1+AB10)^(AA$35-AA10) -> 3.3452697 | AI10: =AA10*(AA10+1)*AD10 -> 103.84669
B11: Issue Date | C11: 45869 | E11: 8 | F11: =$C$7 -> 0.02638 | G11: =$C$10 -> 2.1875 | H11: =G11/(1+F11)^E11 -> 1.7761622 | I11: =H11/H$64 -> 0.020532943 | J11: =I11*E11 -> 0.16426354 | K11: =H11*(1+F11)^(E$35-E11) -> 3.3180197 | M11: =E11*(E11+1)*H11 -> 127.88368 | P11: 8 | Q11: =$C$7 + INT((ROW()-4)/5)*$Q$2 -> 0.02888 | R11: =$C$10 -> 2.1875 | S11: =R11/(1+Q11)^P11 -> 1.7419282 | T11: =S11/S$64 -> 0.032242495 | U11: =T11*P11 -> 0.25793996 | V11: =S11*(1+Q11)^(P$35-P11) -> 3.4497186 | X11: =P11*(P11+1)*S11 -> 125.41883 | AA11: 8 | AB11: =$C$7 + INT((ROW()-4)/5)*(-$Q$2) -> 0.02388 | AC11: =$C$10 -> 2.1875 | AD11: =AC11/(1+AB11)^AA11 -> 1.8111549 | AE11: =AD11/AD$64 -> 0.0085505122 | AF11: =AE11*AA11 -> 0.068404097 | AG11: =AD11*(1+AB11)^(AA$35-AA11) -> 3.1910457 | AI11: =AA11*(AA11+1)*AD11 -> 130.40315
B12: Last Coupon Payment Date | C12: =C11 -> 45869 | E12: 9 | F12: =$C$7 -> 0.02638 | G12: =$C$10 -> 2.1875 | H12: =G12/(1+F12)^E12 -> 1.7305113 | I12: =H12/H$64 -> 0.020005206 | J12: =I12*E12 -> 0.18004685 | K12: =H12*(1+F12)^(E$35-E12) -> 3.1496522 | M12: =E12*(E12+1)*H12 -> 155.74602 | P12: 9 | Q12: =$C$7 + INT((ROW()-4)/5)*$Q$2 -> 0.02888 | R12: =$C$10 -> 2.1875 | S12: =R12/(1+Q12)^P12 -> 1.6930334 | T12: =S12/S$64 -> 0.031337469 | U12: =T12*P12 -> 0.28203722 | V12: =S12*(1+Q12)^(P$35-P12) -> 3.2587738 | X12: =P12*(P12+1)*S12 -> 152.37301 | AA12: 9 | AB12: =$C$7 + INT((ROW()-4)/5)*(-$Q$2) -> 0.02388 | AC12: =$C$10 -> 2.1875 | AD12: =AC12/(1+AB12)^AA12 -> 1.7689132 | AE12: =AD12/AD$64 -> 0.0083510882 | AF12: =AE12*AA12 -> 0.075159794 | AG12: =AD12*(1+AB12)^(AA$35-AA12) -> 3.0439317 | AI12: =AA12*(AA12+1)*AD12 -> 159.20219
B13: Next Coupon Payment Date | C13: =EDATE(C12,6) -> 46053 | E13: 10 | F13: =$C$7 -> 0.02638 | G13: =$C$10 -> 2.1875 | H13: =G13/(1+F13)^E13 -> 1.6860337 | I13: =H13/H$64 -> 0.019491032 | J13: =I13*E13 -> 0.19491032 | K13: =H13*(1+F13)^(E$35-E13) -> 2.9898282 | M13: =E13*(E13+1)*H13 -> 185.46371 | P13: 10 | Q13: =$C$7 + INT((ROW()-4)/5)*$Q$2 -> 0.02888 | R13: =$C$10 -> 2.1875 | S13: =R13/(1+Q13)^P13 -> 1.6455111 | T13: =S13/S$64 -> 0.030457846 | U13: =T13*P13 -> 0.30457846 | V13: =S13*(1+Q13)^(P$35-P13) -> 3.078398 | X13: =P13*(P13+1)*S13 -> 181.00622 | AA13: 10 | AB13: =$C$7 + INT((ROW()-4)/5)*(-$Q$2) -> 0.02388 | AC13: =$C$10 -> 2.1875 | AD13: =AC13/(1+AB13)^AA13 -> 1.7276568 | AE13: =AD13/AD$64 -> 0.0081563154 | AF13: =AE13*AA13 -> 0.081563154 | AG13: =AD13*(1+AB13)^(AA$35-AA13) -> 2.9035999 | AI13: =AA13*(AA13+1)*AD13 -> 190.04224
B14: Settlement Date | C14: =TODAY() -> 46006 | E14: 11 | F14: =$C$7 -> 0.02638 | G14: =$C$10 -> 2.1875 | H14: =G14/(1+F14)^E14 -> 1.6426993 | I14: =H14/H$64 -> 0.018990074 | J14: =I14*E14 -> 0.20889081 | K14: =H14*(1+F14)^(E$35-E14) -> 2.8381142 | M14: =E14*(E14+1)*H14 -> 216.83631 | P14: 11 | Q14: =$C$7 + INT((ROW()-4)/5)*$Q$2 -> 0.03138 | R14: =$C$10 -> 2.1875 | S14: =R14/(1+Q14)^P14 -> 1.5571925 | T14: =S14/S$64 -> 0.028823099 | U14: =T14*P14 -> 0.31705409 | V14: =S14*(1+Q14)^(P$35-P14) -> 2.9794432 | X14: =P14*(P14+1)*S14 -> 205.54941 | AA14: 11 | AB14: =$C$7 + INT((ROW()-4)/5)*(-$Q$2) -> 0.02138 | AC14: =$C$10 -> 2.1875 | AD14: =AC14/(1+AB14)^AA14 -> 1.7333538 | AE14: =AD14/AD$64 -> 0.0081832112 | AF14: =AE14*AA14 -> 0.090015324 | AG14: =AD14*(1+AB14)^(AA$35-AA14) -> 2.7028476 | AI14: =AA14*(AA14+1)*AD14 -> 228.8027
B15: Maturity Date | C15: 56461 | E15: 12 | F15: =$C$7 -> 0.02638 | G15: =$C$10 -> 2.1875 | H15: =G15/(1+F15)^E15 -> 1.6004787 | I15: =H15/H$64 -> 0.018501991 | J15: =I15*E15 -> 0.2220239 | K15: =H15*(1+F15)^(E$35-E15) -> 2.6940987 | M15: =E15*(E15+1)*H15 -> 249.67467 | P15: 12 | Q15: =$C$7 + INT((ROW()-4)/5)*$Q$2 -> 0.03138 | R15: =$C$10 -> 2.1875 | S15: =R15/(1+Q15)^P15 -> 1.5098145 | T15: =S15/S$64 -> 0.027946149 | U15: =T15*P15 -> 0.33535379 | V15: =S15*(1+Q15)^(P$35-P15) -> 2.8009007 | X15: =P15*(P15+1)*S15 -> 235.53106 | AA15: 12 | AB15: =$C$7 + INT((ROW()-4)/5)*(-$Q$2) -> 0.02138 | AC15: =$C$10 -> 2.1875 | AD15: =AC15/(1+AB15)^AA15 -> 1.6970704 | AE15: =AD15/AD$64 -> 0.0080119165 | AF15: =AE15*AA15 -> 0.096142998 | AG15: =AD15*(1+AB15)^(AA$35-AA15) -> 2.5908774 | AI15: =AA15*(AA15+1)*AD15 -> 264.74299
E16: 13 | F16: =$C$7 -> 0.02638 | G16: =$C$10 -> 2.1875 | H16: =G16/(1+F16)^E16 -> 1.5593432 | I16: =H16/H$64 -> 0.018026454 | J16: =I16*E16 -> 0.2343439 | K16: =H16*(1+F16)^(E$35-E16) -> 2.5573911 | M16: =E16*(E16+1)*H16 -> 283.80046 | P16: 13 | Q16: =$C$7 + INT((ROW()-4)/5)*$Q$2 -> 0.03138 | R16: =$C$10 -> 2.1875 | S16: =R16/(1+Q16)^P16 -> 1.463878 | T16: =S16/S$64 -> 0.027095881 | U16: =T16*P16 -> 0.35224645 | V16: =S16*(1+Q16)^(P$35-P16) -> 2.6330572 | X16: =P16*(P16+1)*S16 -> 266.4258 | AA16: 13 | AB16: =$C$7 + INT((ROW()-4)/5)*(-$Q$2) -> 0.02138 | AC16: =$C$10 -> 2.1875 | AD16: =AC16/(1+AB16)^AA16 -> 1.6615466 | AE16: =AD16/AD$64 -> 0.0078442073 | AF16: =AE16*AA16 -> 0.1019747 | AG16: =AD16*(1+AB16)^(AA$35-AA16) -> 2.4835457 | AI16: =AA16*(AA16+1)*AD16 -> 302.40148
E17: 14 | F17: =$C$7 -> 0.02638 | G17: =$C$10 -> 2.1875 | H17: =G17/(1+F17)^E17 -> 1.519265 | I17: =H17/H$64 -> 0.017563138 | J17: =I17*E17 -> 0.24588393 | K17: =H17*(1+F17)^(E$35-E17) -> 2.4276204 | M17: =E17*(E17+1)*H17 -> 319.04565 | P17: 14 | Q17: =$C$7 + INT((ROW()-4)/5)*$Q$2 -> 0.03138 | R17: =$C$10 -> 2.1875 | S17: =R17/(1+Q17)^P17 -> 1.4193392 | T17: =S17/S$64 -> 0.026271481 | U17: =T17*P17 -> 0.36780074 | V17: =S17*(1+Q17)^(P$35-P17) -> 2.4752717 | X17: =P17*(P17+1)*S17 -> 298.06122 | AA17: 14 | AB17: =$C$7 + INT((ROW()-4)/5)*(-$Q$2) -> 0.02138 | AC17: =$C$10 -> 2.1875 | AD17: =AC17/(1+AB17)^AA17 -> 1.6267663 | AE17: =AD17/AD$64 -> 0.0076800087 | AF17: =AE17*AA17 -> 0.10752012 | AG17: =AD17*(1+AB17)^(AA$35-AA17) -> 2.3806605 | AI17: =AA17*(AA17+1)*AD17 -> 341.62092
E18: 15 | F18: =$C$7 -> 0.02638 | G18: =$C$10 -> 2.1875 | H18: =G18/(1+F18)^E18 -> 1.4802169 | I18: =H18/H$64 -> 0.017111731 | J18: =I18*E18 -> 0.25667596 | K18: =H18*(1+F18)^(E$35-E18) -> 2.3044348 | M18: =E18*(E18+1)*H18 -> 355.25205 | P18: 15 | Q18: =$C$7 + INT((ROW()-4)/5)*$Q$2 -> 0.03138 | R18: =$C$10 -> 2.1875 | S18: =R18/(1+Q18)^P18 -> 1.3761554 | T18: =S18/S$64 -> 0.025472165 | U18: =T18*P18 -> 0.38208247 | V18: =S18*(1+Q18)^(P$35-P18) -> 2.3269415 | X18: =P18*(P18+1)*S18 -> 330.2773 | AA18: 15 | AB18: =$C$7 + INT((ROW()-4)/5)*(-$Q$2) -> 0.02138 | AC18: =$C$10 -> 2.1875 | AD18: =AC18/(1+AB18)^AA18 -> 1.5927141 | AE18: =AD18/AD$64 -> 0.0075192472 | AF18: =AE18*AA18 -> 0.11278871 | AG18: =AD18*(1+AB18)^(AA$35-AA18) -> 2.2820374 | AI18: =AA18*(AA18+1)*AD18 -> 382.25138
E19: 16 | F19: =$C$7 -> 0.02638 | G19: =$C$10 -> 2.1875 | H19: =G19/(1+F19)^E19 -> 1.4421724 | I19: =H19/H$64 -> 0.016671925 | J19: =I19*E19 -> 0.2667508 | K19: =H19*(1+F19)^(E$35-E19) -> 2.1875 | M19: =E19*(E19+1)*H19 -> 392.27088 | P19: 16 | Q19: =$C$7 + INT((ROW()-4)/5)*$Q$2 -> 0.03388 | R19: =$C$10 -> 2.1875 | S19: =R19/(1+Q19)^P19 -> 1.2835888 | T19: =S19/S$64 -> 0.023758789 | U19: =T19*P19 -> 0.38014062 | V19: =S19*(1+Q19)^(P$35-P19) -> 2.1875 | X19: =P19*(P19+1)*S19 -> 349.13615 | AA19: 16 | AB19: =$C$7 + INT((ROW()-4)/5)*(-$Q$2) -> 0.01888 | AC19: =$C$10 -> 2.1875 | AD19: =AC19/(1+AB19)^AA19 -> 1.6217334 | AE19: =AD19/AD$64 -> 0.0076562483 | AF19: =AE19*AA19 -> 0.12249997 | AG19: =AD19*(1+AB19)^(AA$35-AA19) -> 2.1875 | AI19: =AA19*(AA19+1)*AD19 -> 441.11149
E20: 17 | F20: =$C$7 -> 0.02638 | G20: =$C$10 -> 2.1875 | H20: =G20/(1+F20)^E20 -> 1.4051057 | I20: =H20/H$64 -> 0.016243424 | J20: =I20*E20 -> 0.2761382 | K20: =H20*(1+F20)^(E$35-E20) -> 2.0764989 | M20: =E20*(E20+1)*H20 -> 429.96234 | P20: 17 | Q20: =$C$7 + INT((ROW()-4)/5)*$Q$2 -> 0.03388 | R20: =$C$10 -> 2.1875 | S20: =R20/(1+Q20)^P20 -> 1.2415259 | T20: =S20/S$64 -> 0.022980219 | U20: =T20*P20 -> 0.39066372 | V20: =S20*(1+Q20)^(P$35-P20) -> 2.0464814 | X20: =P20*(P20+1)*S20 -> 379.90692 | AA20: 17 | AB20: =$C$7 + INT((ROW()-4)/5)*(-$Q$2) -> 0.01888 | AC20: =$C$10 -> 2.1875 | AD20: =AC20/(1+AB20)^AA20 -> 1.5916824 | AE20: =AD20/AD$64 -> 0.0075143769 | AF20: =AE20*AA20 -> 0.12774441 | AG20: =AD20*(1+AB20)^(AA$35-AA20) -> 2.1071817 | AI20: =AA20*(AA20+1)*AD20 -> 487.05483
E21: 18 | F21: =$C$7 -> 0.02638 | G21: =$C$10 -> 2.1875 | H21: =G21/(1+F21)^E21 -> 1.3689917 | I21: =H21/H$64 -> 0.015825936 | J21: =I21*E21 -> 0.28486684 | K21: =H21*(1+F21)^(E$35-E21) -> 1.9711303 | M21: =E21*(E21+1)*H21 -> 468.19515 | P21: 18 | Q21: =$C$7 + INT((ROW()-4)/5)*$Q$2 -> 0.03388 | R21: =$C$10 -> 2.1875 | S21: =R21/(1+Q21)^P21 -> 1.2008414 | T21: =S21/S$64 -> 0.022227163 | U21: =T21*P21 -> 0.40008893 | V21: =S21*(1+Q21)^(P$35-P21) -> 1.9145536 | X21: =P21*(P21+1)*S21 -> 410.68775 | AA21: 18 | AB21: =$C$7 + INT((ROW()-4)/5)*(-$Q$2) -> 0.01888 | AC21: =$C$10 -> 2.1875 | AD21: =AC21/(1+AB21)^AA21 -> 1.5621883 | AE21: =AD21/AD$64 -> 0.0073751343 | AF21: =AE21*AA21 -> 0.13275242 | AG21: =AD21*(1+AB21)^(AA$35-AA21) -> 2.0298125 | AI21: =AA21*(AA21+1)*AD21 -> 534.26841
E22: 19 | F22: =$C$7 -> 0.02638 | G22: =$C$10 -> 2.1875 | H22: =G22/(1+F22)^E22 -> 1.3338059 | I22: =H22/H$64 -> 0.015419178 | J22: =I22*E22 -> 0.29296437 | K22: =H22*(1+F22)^(E$35-E22) -> 1.8711085 | M22: =E22*(E22+1)*H22 -> 506.84623 | P22: 19 | Q22: =$C$7 + INT((ROW()-4)/5)*$Q$2 -> 0.03388 | R22: =$C$10 -> 2.1875 | S22: =R22/(1+Q22)^P22 -> 1.1614901 | T22: =S22/S$64 -> 0.021498784 | U22: =T22*P22 -> 0.40847689 | V22: =S22*(1+Q22)^(P$35-P22) -> 1.7911306 | X22: =P22*(P22+1)*S22 -> 441.36624 | AA22: 19 | AB22: =$C$7 + INT((ROW()-4)/5)*(-$Q$2) -> 0.01888 | AC22: =$C$10 -> 2.1875 | AD22: =AC22/(1+AB22)^AA22 -> 1.5332407 | AE22: =AD22/AD$64 -> 0.007238472 | AF22: =AE22*AA22 -> 0.13753097 | AG22: =AD22*(1+AB22)^(AA$35-AA22) -> 1.955284 | AI22: =AA22*(AA22+1)*AD22 -> 582.63148
E23: 20 | F23: =$C$7 -> 0.02638 | G23: =$C$10 -> 2.1875 | H23: =G23/(1+F23)^E23 -> 1.2995244 | I23: =H23/H$64 -> 0.015022874 | J23: =I23*E23 -> 0.30045748 | K23: =H23*(1+F23)^(E$35-E23) -> 1.7761622 | M23: =E23*(E23+1)*H23 -> 545.80026 | P23: 20 | Q23: =$C$7 + INT((ROW()-4)/5)*$Q$2 -> 0.03388 | R23: =$C$10 -> 2.1875 | S23: =R23/(1+Q23)^P23 -> 1.1234283 | T23: =S23/S$64 -> 0.020794274 | U23: =T23*P23 -> 0.41588548 | V23: =S23*(1+Q23)^(P$35-P23) -> 1.6756642 | X23: =P23*(P23+1)*S23 -> 471.83991 | AA23: 20 | AB23: =$C$7 + INT((ROW()-4)/5)*(-$Q$2) -> 0.01888 | AC23: =$C$10 -> 2.1875 | AD23: =AC23/(1+AB23)^AA23 -> 1.5048296 | AE23: =AD23/AD$64 -> 0.007104342 | AF23: =AE23*AA23 -> 0.14208684 | AG23: =AD23*(1+AB23)^(AA$35-AA23) -> 1.8834919 | AI23: =AA23*(AA23+1)*AD23 -> 632.02842
E24: 21 | F24: =$C$7 -> 0.02638 | G24: =$C$10 -> 2.1875 | H24: =G24/(1+F24)^E24 -> 1.2661241 | I24: =H24/H$64 -> 0.014636757 | J24: =I24*E24 -> 0.30737189 | K24: =H24*(1+F24)^(E$35-E24) -> 1.6860337 | M24: =E24*(E24+1)*H24 -> 584.94932 | P24: 21 | Q24: =$C$7 + INT((ROW()-4)/5)*$Q$2 -> 0.03638 | R24: =$C$10 -> 2.1875 | S24: =R24/(1+Q24)^P24 -> 1.0328769 | T24: =S24/S$64 -> 0.019118198 | U24: =T24*P24 -> 0.40148215 | V24: =S24*(1+Q24)^(P$35-P24) -> 1.5302339 | X24: =P24*(P24+1)*S24 -> 477.18913 | AA24: 21 | AB24: =$C$7 + INT((ROW()-4)/5)*(-$Q$2) -> 0.01638 | AC24: =$C$10 -> 2.1875 | AD24: =AC24/(1+AB24)^AA24 -> 1.5551409 | AE24: =AD24/AD$64 -> 0.0073418632 | AF24: =AE24*AA24 -> 0.15417913 | AG24: =AD24*(1+AB24)^(AA$35-AA24) -> 1.8594605 | AI24: =AA24*(AA24+1)*AD24 -> 718.47509
E25: 22 | F25: =$C$7 -> 0.02638 | G25: =$C$10 -> 2.1875 | H25: =G25/(1+F25)^E25 -> 1.2335822 | I25: =H25/H$64 -> 0.014260563 | J25: =I25*E25 -> 0.31373238 | K25: =H25*(1+F25)^(E$35-E25) -> 1.6004787 | M25: =E25*(E25+1)*H25 -> 624.19258 | P25: 22 | Q25: =$C$7 + INT((ROW()-4)/5)*$Q$2 -> 0.03638 | R25: =$C$10 -> 2.1875 | S25: =R25/(1+Q25)^P25 -> 0.99661988 | T25: =S25/S$64 -> 0.018447092 | U25: =T25*P25 -> 0.40583603 | W25: =SUM(V4:V24) -> 63.248551 | X25: =P25*(P25+1)*S25 -> 504.28966 | AA25: 22 | AB25: =$C$7 + INT((ROW()-4)/5)*(-$Q$2) -> 0.01638 | AC25: =$C$10 -> 2.1875 | AD25: =AC25/(1+AB25)^AA25 -> 1.5300782 | AE25: =AD25/AD$64 -> 0.0072235415 | AF25: =AE25*AA25 -> 0.15891791 | AG25: =AD25*(1+AB25)^(AA$35-AA25) -> 1.8000092 | AI25: =AA25*(AA25+1)*AD25 -> 774.21957
E26: 23 | F26: =$C$7 -> 0.02638 | G26: =$C$10 -> 2.1875 | H26: =G26/(1+F26)^E26 -> 1.2018767 | I26: =H26/H$64 -> 0.013894038 | J26: =I26*E26 -> 0.31956288 | K26: =H26*(1+F26)^(E$35-E26) -> 1.519265 | M26: =E26*(E26+1)*H26 -> 663.43592 | P26: 23 | Q26: =$C$7 + INT((ROW()-4)/5)*$Q$2 -> 0.03638 | R26: =$C$10 -> 2.1875 | S26: =R26/(1+Q26)^P26 -> 0.96163558 | T26: =S26/S$64 -> 0.017799545 | U26: =T26*P26 -> 0.40938954 | X26: =P26*(P26+1)*S26 -> 530.82284 | AA26: 23 | AB26: =$C$7 + INT((ROW()-4)/5)*(-$Q$2) -> 0.01638 | AC26: =$C$10 -> 2.1875 | AD26: =AC26/(1+AB26)^AA26 -> 1.5054194 | AE26: =AD26/AD$64 -> 0.0071071268 | AF26: =AE26*AA26 -> 0.16346392 | AG26: =AD26*(1+AB26)^(AA$35-AA26) -> 1.7424588 | AI26: =AA26*(AA26+1)*AD26 -> 830.99153
E27: 24 | F27: =$C$7 -> 0.02638 | G27: =$C$10 -> 2.1875 | H27: =G27/(1+F27)^E27 -> 1.1709861 | I27: =H27/H$64 -> 0.013536934 | J27: =I27*E27 -> 0.32488641 | K27: =H27*(1+F27)^(E$35-E27) -> 1.4421724 | M27: =E27*(E27+1)*H27 -> 702.59163 | P27: 24 | Q27: =$C$7 + INT((ROW()-4)/5)*$Q$2 -> 0.03638 | R27: =$C$10 -> 2.1875 | S27: =R27/(1+Q27)^P27 -> 0.92787933 | T27: =S27/S$64 -> 0.017174728 | U27: =T27*P27 -> 0.41219348 | X27: =P27*(P27+1)*S27 -> 556.7276 | AA27: 24 | AB27: =$C$7 + INT((ROW()-4)/5)*(-$Q$2) -> 0.01638 | AC27: =$C$10 -> 2.1875 | AD27: =AC27/(1+AB27)^AA27 -> 1.4811581 | AE27: =AD27/AD$64 -> 0.0069925882 | AF27: =AE27*AA27 -> 0.16782212 | AG27: =AD27*(1+AB27)^(AA$35-AA27) -> 1.6867483 | AI27: =AA27*(AA27+1)*AD27 -> 888.69484
E28: 25 | F28: =$C$7 -> 0.02638 | G28: =$C$10 -> 2.1875 | H28: =G28/(1+F28)^E28 -> 1.1408894 | I28: =H28/H$64 -> 0.013189008 | J28: =I28*E28 -> 0.3297252 | K28: =H28*(1+F28)^(E$35-E28) -> 1.3689917 | M28: =E28*(E28+1)*H28 -> 741.5781 | P28: 25 | Q28: =$C$7 + INT((ROW()-4)/5)*$Q$2 -> 0.03638 | R28: =$C$10 -> 2.1875 | S28: =R28/(1+Q28)^P28 -> 0.89530802 | T28: =S28/S$64 -> 0.016571845 | U28: =T28*P28 -> 0.41429612 | X28: =P28*(P28+1)*S28 -> 581.95022 | AA28: 25 | AB28: =$C$7 + INT((ROW()-4)/5)*(-$Q$2) -> 0.01638 | AC28: =$C$10 -> 2.1875 | AD28: =AC28/(1+AB28)^AA28 -> 1.4572877 | AE28: =AD28/AD$64 -> 0.0068798955 | AF28: =AE28*AA28 -> 0.17199739 | AG28: =AD28*(1+AB28)^(AA$35-AA28) -> 1.6328191 | AI28: =AA28*(AA28+1)*AD28 -> 947.237
E29: 26 | F29: =$C$7 -> 0.02638 | G29: =$C$10 -> 2.1875 | H29: =G29/(1+F29)^E29 -> 1.1115663 | I29: =H29/H$64 -> 0.012850024 | J29: =I29*E29 -> 0.33410063 | K29: =H29*(1+F29)^(E$35-E29) -> 1.2995244 | M29: =E29*(E29+1)*H29 -> 780.31952 | P29: 26 | Q29: =$C$7 + INT((ROW()-4)/5)*$Q$2 -> 0.03888 | R29: =$C$10 -> 2.1875 | S29: =R29/(1+Q29)^P29 -> 0.81142435 | T29: =S29/S$64 -> 0.015019187 | U29: =T29*P29 -> 0.39049885 | X29: =P29*(P29+1)*S29 -> 569.6199 | AA29: 26 | AB29: =$C$7 + INT((ROW()-4)/5)*(-$Q$2) -> 0.01388 | AC29: =$C$10 -> 2.1875 | AD29: =AC29/(1+AB29)^AA29 -> 1.5286132 | AE29: =AD29/AD$64 -> 0.0072166251 | AF29: =AE29*AA29 -> 0.18763225 | AG29: =AD29*(1+AB29)^(AA$35-AA29) -> 1.6604161 | AI29: =AA29*(AA29+1)*AD29 -> 1073.0865
E30: 27 | F30: =$C$7 -> 0.02638 | G30: =$C$10 -> 2.1875 | H30: =G30/(1+F30)^E30 -> 1.0829968 | I30: =H30/H$64 -> 0.012519753 | J30: =I30*E30 -> 0.33803333 | K30: =H30*(1+F30)^(E$35-E30) -> 1.2335822 | M30: =E30*(E30+1)*H30 -> 818.74559 | P30: 27 | Q30: =$C$7 + INT((ROW()-4)/5)*$Q$2 -> 0.03888 | R30: =$C$10 -> 2.1875 | S30: =R30/(1+Q30)^P30 -> 0.78105686 | T30: =S30/S$64 -> 0.014457095 | U30: =T30*P30 -> 0.39034156 | X30: =P30*(P30+1)*S30 -> 590.47899 | AA30: 27 | AB30: =$C$7 + INT((ROW()-4)/5)*(-$Q$2) -> 0.01388 | AC30: =$C$10 -> 2.1875 | AD30: =AC30/(1+AB30)^AA30 -> 1.5076865 | AE30: =AD30/AD$64 -> 0.0071178297 | AF30: =AE30*AA30 -> 0.1921814 | AG30: =AD30*(1+AB30)^(AA$35-AA30) -> 1.6152652 | AI30: =AA30*(AA30+1)*AD30 -> 1139.811
E31: 28 | F31: =$C$7 -> 0.02638 | G31: =$C$10 -> 2.1875 | H31: =G31/(1+F31)^E31 -> 1.0551617 | I31: =H31/H$64 -> 0.012197971 | J31: =I31*E31 -> 0.34154318 | K31: =H31*(1+F31)^(E$35-E31) -> 1.1709861 | M31: =E31*(E31+1)*H31 -> 856.79126 | P31: 28 | Q31: =$C$7 + INT((ROW()-4)/5)*$Q$2 -> 0.03888 | R31: =$C$10 -> 2.1875 | S31: =R31/(1+Q31)^P31 -> 0.75182587 | T31: =S31/S$64 -> 0.013916039 | U31: =T31*P31 -> 0.3896491 | X31: =P31*(P31+1)*S31 -> 610.48261 | AA31: 28 | AB31: =$C$7 + INT((ROW()-4)/5)*(-$Q$2) -> 0.01388 | AC31: =$C$10 -> 2.1875 | AD31: =AC31/(1+AB31)^AA31 -> 1.4870463 | AE31: =AD31/AD$64 -> 0.0070203867 | AF31: =AE31*AA31 -> 0.19657083 | AG31: =AD31*(1+AB31)^(AA$35-AA31) -> 1.571342 | AI31: =AA31*(AA31+1)*AD31 -> 1207.4816
E32: 29 | F32: =$C$7 -> 0.02638 | G32: =$C$10 -> 2.1875 | H32: =G32/(1+F32)^E32 -> 1.0280419 | I32: =H32/H$64 -> 0.011884459 | J32: =I32*E32 -> 0.3446493 | K32: =H32*(1+F32)^(E$35-E32) -> 1.1115663 | M32: =E32*(E32+1)*H32 -> 894.39646 | P32: 29 | Q32: =$C$7 + INT((ROW()-4)/5)*$Q$2 -> 0.03888 | R32: =$C$10 -> 2.1875 | S32: =R32/(1+Q32)^P32 -> 0.72368885 | T32: =S32/S$64 -> 0.013395233 | U32: =T32*P32 -> 0.38846175 | X32: =P32*(P32+1)*S32 -> 629.6093 | AA32: 29 | AB32: =$C$7 + INT((ROW()-4)/5)*(-$Q$2) -> 0.01388 | AC32: =$C$10 -> 2.1875 | AD32: =AC32/(1+AB32)^AA32 -> 1.4666887 | AE32: =AD32/AD$64 -> 0.0069242777 | AF32: =AE32*AA32 -> 0.20080405 | AG32: =AD32*(1+AB32)^(AA$35-AA32) -> 1.5286132 | AI32: =AA32*(AA32+1)*AD32 -> 1276.0191
E33: 30 | F33: =$C$7 -> 0.02638 | G33: =$C$10 -> 2.1875 | H33: =G33/(1+F33)^E33 -> 1.0016192 | I33: =H33/H$64 -> 0.011579004 | J33: =I33*E33 -> 0.34737013 | K33: =H33*(1+F33)^(E$35-E33) -> 1.0551617 | M33: =E33*(E33+1)*H33 -> 931.50585 | P33: 30 | Q33: =$C$7 + INT((ROW()-4)/5)*$Q$2 -> 0.03888 | R33: =$C$10 -> 2.1875 | S33: =R33/(1+Q33)^P33 -> 0.69660485 | T33: =S33/S$64 -> 0.012893917 | U33: =T33*P33 -> 0.38681751 | X33: =P33*(P33+1)*S33 -> 647.84251 | AA33: 30 | AB33: =$C$7 + INT((ROW()-4)/5)*(-$Q$2) -> 0.01388 | AC33: =$C$10 -> 2.1875 | AD33: =AC33/(1+AB33)^AA33 -> 1.4466097 | AE33: =AD33/AD$64 -> 0.0068294845 | AF33: =AE33*AA33 -> 0.20488453 | AG33: =AD33*(1+AB33)^(AA$35-AA33) -> 1.4870463 | AI33: =AA33*(AA33+1)*AD33 -> 1345.347
E34: 31 | F34: =$C$7 -> 0.02638 | G34: =$C$10 -> 2.1875 | H34: =G34/(1+F34)^E34 -> 0.97587559 | I34: =H34/H$64 -> 0.011281401 | J34: =I34*E34 -> 0.34972343 | K34: =H34*(1+F34)^(E$35-E34) -> 1.0016192 | M34: =E34*(E34+1)*H34 -> 968.06859 | P34: 31 | Q34: =$C$7 + INT((ROW()-4)/5)*$Q$2 -> 0.04138 | R34: =$C$10 -> 2.1875 | S34: =R34/(1+Q34)^P34 -> 0.62238891 | T34: =S34/S$64 -> 0.011520206 | U34: =T34*P34 -> 0.35712637 | X34: =P34*(P34+1)*S34 -> 617.4098 | AA34: 31 | AB34: =$C$7 + INT((ROW()-4)/5)*(-$Q$2) -> 0.01138 | AC34: =$C$10 -> 2.1875 | AD34: =AC34/(1+AB34)^AA34 -> 1.5402913 | AE34: =AD34/AD$64 -> 0.0072717579 | AF34: =AE34*AA34 -> 0.22542449 | AG34: =AD34*(1+AB34)^(AA$35-AA34) -> 1.5578198 | AI34: =AA34*(AA34+1)*AD34 -> 1527.969
E35: 32 | F35: =$C$7 -> 0.02638 | G35: =$C$10 -> 2.1875 | H35: =G35/(1+F35)^E35 -> 0.95079366 | I35: =H35/H$64 -> 0.010991447 | J35: =I35*E35 -> 0.3517263 | K35: =H35*(1+F35)^(E$35-E35) -> 0.95079366 | L35: =SUM(K4:K35) -> 76.362161 | M35: =E35*(E35+1)*H35 -> 1004.0381 | P35: 32 | Q35: =$C$7 + INT((ROW()-4)/5)*$Q$2 -> 0.04138 | R35: =$C$10 -> 2.1875 | S35: =R35/(1+Q35)^P35 -> 0.59765783 | T35: =S35/S$64 -> 0.011062442 | U35: =T35*P35 -> 0.35399813 | X35: =P35*(P35+1)*S35 -> 631.12667 | AA35: 32 | AB35: =$C$7 + INT((ROW()-4)/5)*(-$Q$2) -> 0.01138 | AC35: =$C$10 -> 2.1875 | AD35: =AC35/(1+AB35)^AA35 -> 1.52296 | AE35: =AD35/AD$64 -> 0.0071899364 | AF35: =AE35*AA35 -> 0.23007796 | AG35: =AD35*(1+AB35)^(AA$35-AA35) -> 1.52296 | AI35: =AA35*(AA35+1)*AD35 -> 1608.2458
E36: 33 | F36: =$C$7 -> 0.02638 | G36: =$C$10 -> 2.1875 | H36: =G36/(1+F36)^E36 -> 0.92635638 | I36: =H36/H$64 -> 0.010708945 | J36: =I36*E36 -> 0.35339518 | M36: =E36*(E36+1)*H36 -> 1039.3719 | P36: 33 | Q36: =$C$7 + INT((ROW()-4)/5)*$Q$2 -> 0.04138 | R36: =$C$10 -> 2.1875 | S36: =R36/(1+Q36)^P36 -> 0.57390946 | T36: =S36/S$64 -> 0.010622867 | U36: =T36*P36 -> 0.35055463 | X36: =P36*(P36+1)*S36 -> 643.92641 | AA36: 33 | AB36: =$C$7 + INT((ROW()-4)/5)*(-$Q$2) -> 0.01138 | AC36: =$C$10 -> 2.1875 | AD36: =AC36/(1+AB36)^AA36 -> 1.5058237 | AE36: =AD36/AD$64 -> 0.0071090356 | AF36: =AE36*AA36 -> 0.23459817 | AG36: =AD36*(1+AB36)^(AA$35-AA36) -> 1.4888803 | AI36: =AA36*(AA36+1)*AD36 -> 1689.5342
E37: 34 | F37: =$C$7 -> 0.02638 | G37: =$C$10 -> 2.1875 | H37: =G37/(1+F37)^E37 -> 0.90254718 | I37: =H37/H$64 -> 0.010433704 | J37: =I37*E37 -> 0.35474593 | M37: =E37*(E37+1)*H37 -> 1074.0311 | P37: 34 | Q37: =$C$7 + INT((ROW()-4)/5)*$Q$2 -> 0.04138 | R37: =$C$10 -> 2.1875 | S37: =R37/(1+Q37)^P37 -> 0.55110475 | T37: =S37/S$64 -> 0.01020076 | U37: =T37*P37 -> 0.34682584 | X37: =P37*(P37+1)*S37 -> 655.81465 | AA37: 34 | AB37: =$C$7 + INT((ROW()-4)/5)*(-$Q$2) -> 0.01138 | AC37: =$C$10 -> 2.1875 | AD37: =AC37/(1+AB37)^AA37 -> 1.4888803 | AE37: =AD37/AD$64 -> 0.007029045 | AF37: =AE37*AA37 -> 0.23898753 | AG37: =AD37*(1+AB37)^(AA$35-AA37) -> 1.4555632 | AI37: =AA37*(AA37+1)*AD37 -> 1771.7675
E38: 35 | F38: =$C$7 -> 0.02638 | G38: =$C$10 -> 2.1875 | H38: =G38/(1+F38)^E38 -> 0.87934993 | I38: =H38/H$64 -> 0.010165537 | J38: =I38*E38 -> 0.35579379 | M38: =E38*(E38+1)*H38 -> 1107.9809 | P38: 35 | Q38: =$C$7 + INT((ROW()-4)/5)*$Q$2 -> 0.04138 | R38: =$C$10 -> 2.1875 | S38: =R38/(1+Q38)^P38 -> 0.52920619 | T38: =S38/S$64 -> 0.0097954253 | U38: =T38*P38 -> 0.34283989 | X38: =P38*(P38+1)*S38 -> 666.7998 | AA38: 35 | AB38: =$C$7 + INT((ROW()-4)/5)*(-$Q$2) -> 0.01138 | AC38: =$C$10 -> 2.1875 | AD38: =AC38/(1+AB38)^AA38 -> 1.4721275 | AE38: =AD38/AD$64 -> 0.0069499546 | AF38: =AE38*AA38 -> 0.24324841 | AG38: =AD38*(1+AB38)^(AA$35-AA38) -> 1.4229916 | AI38: =AA38*(AA38+1)*AD38 -> 1854.8806
E39: 36 | F39: =$C$7 -> 0.02638 | G39: =$C$10 -> 2.1875 | H39: =G39/(1+F39)^E39 -> 0.85674889 | I39: =H39/H$64 -> 0.0099042624 | J39: =I39*E39 -> 0.35655345 | M39: =E39*(E39+1)*H39 -> 1141.1895 | P39: 36 | Q39: =$C$7 + INT((ROW()-4)/5)*$Q$2 -> 0.04388 | R39: =$C$10 -> 2.1875 | S39: =R39/(1+Q39)^P39 -> 0.46615172 | T39: =S39/S$64 -> 0.0086283087 | U39: =T39*P39 -> 0.31061911 | X39: =P39*(P39+1)*S39 -> 620.91409 | AA39: 36 | AB39: =$C$7 + INT((ROW()-4)/5)*(-$Q$2) -> 0.00888 | AC39: =$C$10 -> 2.1875 | AD39: =AC39/(1+AB39)^AA39 -> 1.5912031 | AE39: =AD39/AD$64 -> 0.0075121137 | AF39: =AE39*AA39 -> 0.27043609 | AG39: =AD39*(1+AB39)^(AA$35-AA39) -> 1.5359163 | AI39: =AA39*(AA39+1)*AD39 -> 2119.4825
E40: 37 | F40: =$C$7 -> 0.02638 | G40: =$C$10 -> 2.1875 | H40: =G40/(1+F40)^E40 -> 0.83472875 | I40: =H40/H$64 -> 0.0096497032 | J40: =I40*E40 -> 0.35703902 | M40: =E40*(E40+1)*H40 -> 1173.6286 | P40: 37 | Q40: =$C$7 + INT((ROW()-4)/5)*$Q$2 -> 0.04388 | R40: =$C$10 -> 2.1875 | S40: =R40/(1+Q40)^P40 -> 0.44655681 | T40: =S40/S$64 -> 0.0082656135 | U40: =T40*P40 -> 0.3058277 | X40: =P40*(P40+1)*S40 -> 627.85887 | AA40: 37 | AB40: =$C$7 + INT((ROW()-4)/5)*(-$Q$2) -> 0.00888 | AC40: =$C$10 -> 2.1875 | AD40: =AC40/(1+AB40)^AA40 -> 1.5771975 | AE40: =AD40/AD$64 -> 0.0074459932 | AF40: =AE40*AA40 -> 0.27550175 | AG40: =AD40*(1+AB40)^(AA$35-AA40) -> 1.5089975 | AI40: =AA40*(AA40+1)*AD40 -> 2217.5397
E41: 38 | F41: =$C$7 -> 0.02638 | G41: =$C$10 -> 2.1875 | H41: =G41/(1+F41)^E41 -> 0.81327457 | I41: =H41/H$64 -> 0.0094016867 | J41: =I41*E41 -> 0.3572641 | M41: =E41*(E41+1)*H41 -> 1205.2729 | P41: 38 | Q41: =$C$7 + INT((ROW()-4)/5)*$Q$2 -> 0.04388 | R41: =$C$10 -> 2.1875 | S41: =R41/(1+Q41)^P41 -> 0.42778558 | T41: =S41/S$64 -> 0.0079181645 | U41: =T41*P41 -> 0.30089025 | X41: =P41*(P41+1)*S41 -> 633.97823 | AA41: 38 | AB41: =$C$7 + INT((ROW()-4)/5)*(-$Q$2) -> 0.00888 | AC41: =$C$10 -> 2.1875 | AD41: =AC41/(1+AB41)^AA41 -> 1.5633153 | AE41: =AD41/AD$64 -> 0.0073804548 | AF41: =AE41*AA41 -> 0.28045728 | AG41: =AD41*(1+AB41)^(AA$35-AA41) -> 1.4825505 | AI41: =AA41*(AA41+1)*AD41 -> 2316.8333
E42: 39 | F42: =$C$7 -> 0.02638 | G42: =$C$10 -> 2.1875 | H42: =G42/(1+F42)^E42 -> 0.7923718 | I42: =H42/H$64 -> 0.0091600447 | J42: =I42*E42 -> 0.35724175 | M42: =E42*(E42+1)*H42 -> 1236.1 | P42: 39 | Q42: =$C$7 + INT((ROW()-4)/5)*$Q$2 -> 0.04388 | R42: =$C$10 -> 2.1875 | S42: =R42/(1+Q42)^P42 -> 0.40980341 | T42: =S42/S$64 -> 0.0075853206 | U42: =T42*P42 -> 0.2958275 | X42: =P42*(P42+1)*S42 -> 639.29331 | AA42: 39 | AB42: =$C$7 + INT((ROW()-4)/5)*(-$Q$2) -> 0.00888 | AC42: =$C$10 -> 2.1875 | AD42: =AC42/(1+AB42)^AA42 -> 1.5495553 | AE42: =AD42/AD$64 -> 0.0073154932 | AF42: =AE42*AA42 -> 0.28530424 | AG42: =AD42*(1+AB42)^(AA$35-AA42) -> 1.456567 | AI42: =AA42*(AA42+1)*AD42 -> 2417.3062
E43: 40 | F43: =$C$7 -> 0.02638 | G43: =$C$10 -> 2.1875 | H43: =G43/(1+F43)^E43 -> 0.77200627 | I43: =H43/H$64 -> 0.0089246134 | J43: =I43*E43 -> 0.35698454 | M43: =E43*(E43+1)*H43 -> 1266.0903 | P43: 40 | Q43: =$C$7 + INT((ROW()-4)/5)*$Q$2 -> 0.04388 | R43: =$C$10 -> 2.1875 | S43: =R43/(1+Q43)^P43 -> 0.39257712 | T43: =S43/S$64 -> 0.007266468 | U43: =T43*P43 -> 0.29065872 | X43: =P43*(P43+1)*S43 -> 643.82648 | AA43: 40 | AB43: =$C$7 + INT((ROW()-4)/5)*(-$Q$2) -> 0.00888 | AC43: =$C$10 -> 2.1875 | AD43: =AC43/(1+AB43)^AA43 -> 1.5359163 | AE43: =AD43/AD$64 -> 0.0072511034 | AF43: =AE43*AA43 -> 0.29004414 | AG43: =AD43*(1+AB43)^(AA$35-AA43) -> 1.4310389 | AI43: =AA43*(AA43+1)*AD43 -> 2518.9028
E44: 41 | F44: =$C$7 -> 0.02638 | G44: =$C$10 -> 2.1875 | H44: =G44/(1+F44)^E44 -> 0.75216418 | I44: =H44/H$64 -> 0.0086952332 | J44: =I44*E44 -> 0.35650456 | M44: =E44*(E44+1)*H44 -> 1295.2267 | P44: 41 | Q44: =$C$7 + INT((ROW()-4)/5)*$Q$2 -> 0.04638 | R44: =$C$10 -> 2.1875 | S44: =R44/(1+Q44)^P44 -> 0.34094272 | T44: =S44/S$64 -> 0.006310733 | U44: =T44*P44 -> 0.25874005 | X44: =P44*(P44+1)*S44 -> 587.10337 | AA44: 41 | AB44: =$C$7 + INT((ROW()-4)/5)*(-$Q$2) -> 0.00638 | AC44: =$C$10 -> 2.1875 | AD44: =AC44/(1+AB44)^AA44 -> 1.6854123 | AE44: =AD44/AD$64 -> 0.0079568783 | AF44: =AE44*AA44 -> 0.32623201 | AG44: =AD44*(1+AB44)^(AA$35-AA44) -> 1.5916523 | AI44: =AA44*(AA44+1)*AD44 -> 2902.2801
E45: 42 | F45: =$C$7 -> 0.02638 | G45: =$C$10 -> 2.1875 | H45: =G45/(1+F45)^E45 -> 0.73283207 | I45: =H45/H$64 -> 0.0084717485 | J45: =I45*E45 -> 0.35581344 | M45: =E45*(E45+1)*H45 -> 1323.4947 | P45: 42 | Q45: =$C$7 + INT((ROW()-4)/5)*$Q$2 -> 0.04638 | R45: =$C$10 -> 2.1875 | S45: =R45/(1+Q45)^P45 -> 0.32583069 | T45: =S45/S$64 -> 0.0060310145 | U45: =T45*P45 -> 0.25330261 | X45: =P45*(P45+1)*S45 -> 588.45024 | AA45: 42 | AB45: =$C$7 + INT((ROW()-4)/5)*(-$Q$2) -> 0.00638 | AC45: =$C$10 -> 2.1875 | AD45: =AC45/(1+AB45)^AA45 -> 1.6747276 | AE45: =AD45/AD$64 -> 0.0079064352 | AF45: =AE45*AA45 -> 0.33207028 | AG45: =AD45*(1+AB45)^(AA$35-AA45) -> 1.5715355 | AI45: =AA45*(AA45+1)*AD45 -> 3024.558
E46: 43 | F46: =$C$7 -> 0.02638 | G46: =$C$10 -> 2.1875 | H46: =G46/(1+F46)^E46 -> 0.71399684 | I46: =H46/H$64 -> 0.0082540077 | J46: =I46*E46 -> 0.35492233 | M46: =E46*(E46+1)*H46 -> 1350.882 | P46: 43 | Q46: =$C$7 + INT((ROW()-4)/5)*$Q$2 -> 0.04638 | R46: =$C$10 -> 2.1875 | S46: =R46/(1+Q46)^P46 -> 0.3113885 | T46: =S46/S$64 -> 0.0057636944 | U46: =T46*P46 -> 0.24783886 | X46: =P46*(P46+1)*S46 -> 589.14704 | AA46: 43 | AB46: =$C$7 + INT((ROW()-4)/5)*(-$Q$2) -> 0.00638 | AC46: =$C$10 -> 2.1875 | AD46: =AC46/(1+AB46)^AA46 -> 1.6641106 | AE46: =AD46/AD$64 -> 0.007856312 | AF46: =AE46*AA46 -> 0.33782141 | AG46: =AD46*(1+AB46)^(AA$35-AA46) -> 1.551673 | AI46: =AA46*(AA46+1)*AD46 -> 3148.4972
E47: 44 | F47: =$C$7 -> 0.02638 | G47: =$C$10 -> 2.1875 | H47: =G47/(1+F47)^E47 -> 0.6956457 | I47: =H47/H$64 -> 0.0080418634 | J47: =I47*E47 -> 0.35384199 | M47: =E47*(E47+1)*H47 -> 1377.3785 | P47: 44 | Q47: =$C$7 + INT((ROW()-4)/5)*$Q$2 -> 0.04638 | R47: =$C$10 -> 2.1875 | S47: =R47/(1+Q47)^P47 -> 0.29758644 | T47: =S47/S$64 -> 0.005508223 | U47: =T47*P47 -> 0.24236181 | X47: =P47*(P47+1)*S47 -> 589.22115 | AA47: 44 | AB47: =$C$7 + INT((ROW()-4)/5)*(-$Q$2) -> 0.00638 | AC47: =$C$10 -> 2.1875 | AD47: =AC47/(1+AB47)^AA47 -> 1.6535608 | AE47: =AD47/AD$64 -> 0.0078065065 | AF47: =AE47*AA47 -> 0.34348628 | AG47: =AD47*(1+AB47)^(AA$35-AA47) -> 1.5320615 | AI47: =AA47*(AA47+1)*AD47 -> 3274.0505
E48: 45 | F48: =$C$7 -> 0.02638 | G48: =$C$10 -> 2.1875 | H48: =G48/(1+F48)^E48 -> 0.67776623 | I48: =H48/H$64 -> 0.0078351716 | J48: =I48*E48 -> 0.35258272 | M48: =E48*(E48+1)*H48 -> 1402.9761 | P48: 45 | Q48: =$C$7 + INT((ROW()-4)/5)*$Q$2 -> 0.04638 | R48: =$C$10 -> 2.1875 | S48: =R48/(1+Q48)^P48 -> 0.28439614 | T48: =S48/S$64 -> 0.0052640752 | U48: =T48*P48 -> 0.23688338 | X48: =P48*(P48+1)*S48 -> 588.70002 | AA48: 45 | AB48: =$C$7 + INT((ROW()-4)/5)*(-$Q$2) -> 0.00638 | AC48: =$C$10 -> 2.1875 | AD48: =AC48/(1+AB48)^AA48 -> 1.643078 | AE48: =AD48/AD$64 -> 0.0077570167 | AF48: =AE48*AA48 -> 0.34906575 | AH48: =SUM(AG4:AG47) -> 97.871222 | AI48: =AA48*(AA48+1)*AD48 -> 3401.1715
E49: 46 | F49: =$C$7 -> 0.02638 | G49: =$C$10 -> 2.1875 | H49: =G49/(1+F49)^E49 -> 0.66034629 | I49: =H49/H$64 -> 0.0076337921 | J49: =I49*E49 -> 0.35115444 | M49: =E49*(E49+1)*H49 -> 1427.6687 | P49: 46 | Q49: =$C$7 + INT((ROW()-4)/5)*$Q$2 -> 0.04888 | R49: =$C$10 -> 2.1875 | S49: =R49/(1+Q49)^P49 -> 0.24353482 | T49: =S49/S$64 -> 0.004507746 | U49: =T49*P49 -> 0.20735632 | X49: =P49*(P49+1)*S49 -> 526.52228 | AA49: 46 | AB49: =$C$7 + INT((ROW()-4)/5)*(-$Q$2) -> 0.00388 | AC49: =$C$10 -> 2.1875 | AD49: =AC49/(1+AB49)^AA49 -> 1.8305651 | AE49: =AD49/AD$64 -> 0.0086421483 | AF49: =AE49*AA49 -> 0.39753882 | AI49: =AA49*(AA49+1)*AD49 -> 3957.6817
E50: 47 | F50: =$C$7 -> 0.02638 | G50: =$C$10 -> 2.1875 | H50: =G50/(1+F50)^E50 -> 0.64337409 | I50: =H50/H$64 -> 0.0074375885 | J50: =I50*E50 -> 0.34956666 | M50: =E50*(E50+1)*H50 -> 1451.4519 | P50: 47 | Q50: =$C$7 + INT((ROW()-4)/5)*$Q$2 -> 0.04888 | R50: =$C$10 -> 2.1875 | S50: =R50/(1+Q50)^P50 -> 0.23218559 | T50: =S50/S$64 -> 0.0042976756 | U50: =T50*P50 -> 0.20199075 | X50: =P50*(P50+1)*S50 -> 523.81068 | AA50: 47 | AB50: =$C$7 + INT((ROW()-4)/5)*(-$Q$2) -> 0.00388 | AC50: =$C$10 -> 2.1875 | AD50: =AC50/(1+AB50)^AA50 -> 1.8234899 | AE50: =AD50/AD$64 -> 0.0086087464 | AF50: =AE50*AA50 -> 0.40461108 | AI50: =AA50*(AA50+1)*AD50 -> 4113.7933
E51: 48 | F51: =$C$7 -> 0.02638 | G51: =$C$10 -> 2.1875 | H51: =G51/(1+F51)^E51 -> 0.6268381 | I51: =H51/H$64 -> 0.0072464278 | J51: =I51*E51 -> 0.34782853 | M51: =E51*(E51+1)*H51 -> 1474.3232 | P51: 48 | Q51: =$C$7 + INT((ROW()-4)/5)*$Q$2 -> 0.04888 | R51: =$C$10 -> 2.1875 | S51: =R51/(1+Q51)^P51 -> 0.22136525 | T51: =S51/S$64 -> 0.004097395 | U51: =T51*P51 -> 0.19667496 | X51: =P51*(P51+1)*S51 -> 520.65107 | AA51: 48 | AB51: =$C$7 + INT((ROW()-4)/5)*(-$Q$2) -> 0.00388 | AC51: =$C$10 -> 2.1875 | AD51: =AC51/(1+AB51)^AA51 -> 1.8164421 | AE51: =AD51/AD$64 -> 0.0085754735 | AF51: =AE51*AA51 -> 0.41162273 | AI51: =AA51*(AA51+1)*AD51 -> 4272.2719
E52: 49 | F52: =$C$7 -> 0.02638 | G52: =$C$10 -> 2.1875 | H52: =G52/(1+F52)^E52 -> 0.61072712 | I52: =H52/H$64 -> 0.0070601802 | J52: =I52*E52 -> 0.34594883 | M52: =E52*(E52+1)*H52 -> 1496.2814 | P52: 49 | Q52: =$C$7 + INT((ROW()-4)/5)*$Q$2 -> 0.04888 | R52: =$C$10 -> 2.1875 | S52: =R52/(1+Q52)^P52 -> 0.21104917 | T52: =S52/S$64 -> 0.0039064478 | U52: =T52*P52 -> 0.19141594 | X52: =P52*(P52+1)*S52 -> 517.07046 | AA52: 49 | AB52: =$C$7 + INT((ROW()-4)/5)*(-$Q$2) -> 0.00388 | AC52: =$C$10 -> 2.1875 | AD52: =AC52/(1+AB52)^AA52 -> 1.8094216 | AE52: =AD52/AD$64 -> 0.0085423293 | AF52: =AE52*AA52 -> 0.41857414 | AI52: =AA52*(AA52+1)*AD52 -> 4433.0829
E53: 50 | F53: =$C$7 -> 0.02638 | G53: =$C$10 -> 2.1875 | H53: =G53/(1+F53)^E53 -> 0.59503022 | I53: =H53/H$64 -> 0.0068787196 | J53: =I53*E53 -> 0.34393598 | M53: =E53*(E53+1)*H53 -> 1517.3271 | P53: 50 | Q53: =$C$7 + INT((ROW()-4)/5)*$Q$2 -> 0.04888 | R53: =$C$10 -> 2.1875 | S53: =R53/(1+Q53)^P53 -> 0.20121384 | T53: =S53/S$64 -> 0.0037243992 | U53: =T53*P53 -> 0.18621996 | X53: =P53*(P53+1)*S53 -> 513.09528 | AA53: 50 | AB53: =$C$7 + INT((ROW()-4)/5)*(-$Q$2) -> 0.00388 | AC53: =$C$10 -> 2.1875 | AD53: =AC53/(1+AB53)^AA53 -> 1.8024282 | AE53: =AD53/AD$64 -> 0.0085093132 | AF53: =AE53*AA53 -> 0.42546566 | AI53: =AA53*(AA53+1)*AD53 -> 4596.1918
E54: 51 | F54: =$C$7 -> 0.02638 | G54: =$C$10 -> 2.1875 | H54: =G54/(1+F54)^E54 -> 0.57973676 | I54: =H54/H$64 -> 0.0067019229 | J54: =I54*E54 -> 0.34179807 | M54: =E54*(E54+1)*H54 -> 1537.4619 | P54: 51 | Q54: =$C$7 + INT((ROW()-4)/5)*$Q$2 -> 0.05138 | R54: =$C$10 -> 2.1875 | S54: =R54/(1+Q54)^P54 -> 0.16990368 | T54: =S54/S$64 -> 0.0031448589 | U54: =T54*P54 -> 0.1603878 | X54: =P54*(P54+1)*S54 -> 450.58456 | AA54: 51 | AB54: =$C$7 + INT((ROW()-4)/5)*(-$Q$2) -> 0.00138 | AC54: =$C$10 -> 2.1875 | AD54: =AC54/(1+AB54)^AA54 -> 2.0389355 | AE54: =AD54/AD$64 -> 0.0096258709 | AF54: =AE54*AA54 -> 0.49091942 | AI54: =AA54*(AA54+1)*AD54 -> 5407.2569
E55: 52 | F55: =$C$7 -> 0.02638 | G55: =$C$10 -> 2.1875 | H55: =G55/(1+F55)^E55 -> 0.56483638 | I55: =H55/H$64 -> 0.0065296702 | J55: =I55*E55 -> 0.33954285 | M55: =E55*(E55+1)*H55 -> 1556.6891 | P55: 52 | Q55: =$C$7 + INT((ROW()-4)/5)*$Q$2 -> 0.05138 | R55: =$C$10 -> 2.1875 | S55: =R55/(1+Q55)^P55 -> 0.16160064 | T55: =S55/S$64 -> 0.0029911724 | U55: =T55*P55 -> 0.15554097 | X55: =P55*(P55+1)*S55 -> 445.37136 | AA55: 52 | AB55: =$C$7 + INT((ROW()-4)/5)*(-$Q$2) -> 0.00138 | AC55: =$C$10 -> 2.1875 | AD55: =AC55/(1+AB55)^AA55 -> 2.0361256 | AE55: =AD55/AD$64 -> 0.0096126055 | AF55: =AE55*AA55 -> 0.49985549 | AI55: =AA55*(AA55+1)*AD55 -> 5611.5623
E56: 53 | F56: =$C$7 -> 0.02638 | G56: =$C$10 -> 2.1875 | H56: =G56/(1+F56)^E56 -> 0.55031896 | I56: =H56/H$64 -> 0.0063618447 | J56: =I56*E56 -> 0.33717777 | M56: =E56*(E56+1)*H56 -> 1575.0129 | P56: 53 | Q56: =$C$7 + INT((ROW()-4)/5)*$Q$2 -> 0.05138 | R56: =$C$10 -> 2.1875 | S56: =R56/(1+Q56)^P56 -> 0.15370336 | T56: =S56/S$64 -> 0.0028449965 | U56: =T56*P56 -> 0.15078482 | X56: =P56*(P56+1)*S56 -> 439.89902 | AA56: 53 | AB56: =$C$7 + INT((ROW()-4)/5)*(-$Q$2) -> 0.00138 | AC56: =$C$10 -> 2.1875 | AD56: =AC56/(1+AB56)^AA56 -> 2.0333197 | AE56: =AD56/AD$64 -> 0.0095993584 | AF56: =AE56*AA56 -> 0.50876599 | AI56: =AA56*(AA56+1)*AD56 -> 5819.3609
E57: 54 | F57: =$C$7 -> 0.02638 | G57: =$C$10 -> 2.1875 | H57: =G57/(1+F57)^E57 -> 0.53617468 | I57: =H57/H$64 -> 0.0061983327 | J57: =I57*E57 -> 0.33470997 | M57: =E57*(E57+1)*H57 -> 1592.4388 | P57: 54 | Q57: =$C$7 + INT((ROW()-4)/5)*$Q$2 -> 0.05138 | R57: =$C$10 -> 2.1875 | S57: =R57/(1+Q57)^P57 -> 0.14619201 | T57: =S57/S$64 -> 0.0027059641 | U57: =T57*P57 -> 0.14612206 | X57: =P57*(P57+1)*S57 -> 434.19028 | AA57: 54 | AB57: =$C$7 + INT((ROW()-4)/5)*(-$Q$2) -> 0.00138 | AC57: =$C$10 -> 2.1875 | AD57: =AC57/(1+AB57)^AA57 -> 2.0305175 | AE57: =AD57/AD$64 -> 0.0095861295 | AF57: =AE57*AA57 -> 0.51765099 | AI57: =AA57*(AA57+1)*AD57 -> 6030.6371
E58: 55 | F58: =$C$7 -> 0.02638 | G58: =$C$10 -> 2.1875 | H58: =G58/(1+F58)^E58 -> 0.52239392 | I58: =H58/H$64 -> 0.0060390233 | J58: =I58*E58 -> 0.33214628 | M58: =E58*(E58+1)*H58 -> 1608.9733 | P58: 55 | Q58: =$C$7 + INT((ROW()-4)/5)*$Q$2 -> 0.05138 | R58: =$C$10 -> 2.1875 | S58: =R58/(1+Q58)^P58 -> 0.13904774 | T58: =S58/S$64 -> 0.002573726 | U58: =T58*P58 -> 0.14155493 | X58: =P58*(P58+1)*S58 -> 428.26704 | AA58: 55 | AB58: =$C$7 + INT((ROW()-4)/5)*(-$Q$2) -> 0.00138 | AC58: =$C$10 -> 2.1875 | AD58: =AC58/(1+AB58)^AA58 -> 2.0277193 | AE58: =AD58/AD$64 -> 0.0095729189 | AF58: =AE58*AA58 -> 0.52651054 | AI58: =AA58*(AA58+1)*AD58 -> 6245.3754
E59: 56 | F59: =$C$7 -> 0.02638 | G59: =$C$10 -> 2.1875 | H59: =G59/(1+F59)^E59 -> 0.50896737 | I59: =H59/H$64 -> 0.0058838084 | J59: =I59*E59 -> 0.32949327 | M59: =E59*(E59+1)*H59 -> 1624.6238 | P59: 56 | Q59: =$C$7 + INT((ROW()-4)/5)*$Q$2 -> 0.05388 | R59: =$C$10 -> 2.1875 | S59: =R59/(1+Q59)^P59 -> 0.11578251 | T59: =S59/S$64 -> 0.0021430945 | U59: =T59*P59 -> 0.12001329 | X59: =P59*(P59+1)*S59 -> 369.57776 | AA59: 56 | AB59: =$C$7 + INT((ROW()-4)/5)*(-$Q$2) -> -0.00112 | AC59: =$C$10 -> 2.1875 | AD59: =AC59/(1+AB59)^AA59 -> 2.3291758 | AE59: =AD59/AD$64 -> 0.010996104 | AF59: =AE59*AA59 -> 0.6157818 | AI59: =AA59*(AA59+1)*AD59 -> 7434.7293
E60: 57 | F60: =$C$7 -> 0.02638 | G60: =$C$10 -> 2.1875 | H60: =G60/(1+F60)^E60 -> 0.4958859 | I60: =H60/H$64 -> 0.0057325829 | J60: =I60*E60 -> 0.32675722 | M60: =E60*(E60+1)*H60 -> 1639.3988 | P60: 57 | Q60: =$C$7 + INT((ROW()-4)/5)*$Q$2 -> 0.05388 | R60: =$C$10 -> 2.1875 | S60: =R60/(1+Q60)^P60 -> 0.10986308 | T60: =S60/S$64 -> 0.002033528 | U60: =T60*P60 -> 0.1159111 | X60: =P60*(P60+1)*S60 -> 363.20735 | AA60: 57 | AB60: =$C$7 + INT((ROW()-4)/5)*(-$Q$2) -> -0.00112 | AC60: =$C$10 -> 2.1875 | AD60: =AC60/(1+AB60)^AA60 -> 2.3317874 | AE60: =AD60/AD$64 -> 0.011008433 | AF60: =AE60*AA60 -> 0.62748068 | AI60: =AA60*(AA60+1)*AD60 -> 7708.8893
... E62: 59 | F62: =$C$7 -> 0.02638 | G62: =$C$10 -> 2.1875 | H62: =G62/(1+F62)^E62 -> 0.47072297 | I62: =H62/H$64 -> 0.0054416923 | J62: =I62*E62 -> 0.32105984 | M62: =E62*(E62+1)*H62 -> 1666.3593 | P62: 59 | Q62: =$C$7 + INT((ROW()-4)/5)*$Q$2 -> 0.05388 | R62: =$C$10 -> 2.1875 | S62: =R62/(1+Q62)^P62 -> 0.098916663 | T62: =S62/S$64 -> 0.0018309135 | U62: =T62*P62 -> 0.1080239 | X62: =P62*(P62+1)*S62 -> 350.16499 | AA62: 59 | AB62: =$C$7 + INT((ROW()-4)/5)*(-$Q$2) -> -0.00112 | AC62: =$C$10 -> 2.1875 | AD62: =AC62/(1+AB62)^AA62 -> 2.3370194 | AE62: =AD62/AD$64 -> 0.011033133 | AF62: =AE62*AA62 -> 0.65095487 | AI62: =AA62*(AA62+1)*AD62 -> 8273.0488
E63: 60 | F63: =$C$7 -> 0.02638 | G63: =$C$10+$C$5 -> 102.1875 | H63: =G63/(1+F63)^E63 -> 21.424314 | I63: =H63/H$64 -> 0.2476712 | J63: =I63*E63 -> 14.860272 | M63: =E63*(E63+1)*H63 -> 78412.989 | P63: 60 | Q63: =$C$7 + INT((ROW()-4)/5)*$Q$2 -> 0.05388 | R63: =$C$10+$C$5 -> 102.1875 | S63: =R63/(1+Q63)^P63 -> 4.3845801 | T63: =S63/S$64 -> 0.081157075 | U63: =T63*P63 -> 4.8694245 | X63: =P63*(P63+1)*S63 -> 16047.563 | AA63: 60 | AB63: =$C$7 + INT((ROW()-4)/5)*(-$Q$2) -> -0.00112 | AC63: =$C$10+$C$5 -> 102.1875 | AD63: =AC63/(1+AB63)^AA63 -> 109.2946 | AE63: =AD63/AD$64 -> 0.51598285 | AF63: =AE63*AA63 -> 30.958971 | AI63: =AA63*(AA63+1)*AD63 -> 400018.25
H64: =SUM(H4:H63) -> 86.503049 | J64: =SUM(J4:J63) -> 31.960931 | M64: =SUM(M4:M63) -> 130354.03 | S64: =SUM(S4:S63) -> 54.025852 | U64: =SUM(U4:U63) -> 21.130289 | X64: =SUM(X4:X63) -> 41472.718 | AD64: =SUM(AD4:AD63) -> 211.81829 | AF64: =SUM(AF4:AF63) -> 45.807244 | AI64: =SUM(AI4:AI63) -> 532903.03
E66: Macaulay Duration | F66: =J64 -> 31.960931 | P66: Macaulay Duration | Q66: =U64 -> 21.130289 | AA66: Macaulay Duration | AB66: =AF64 -> 45.807244
E67: Modified Duration | F67: =F66/(1+$C$6) -> 30.359181 | P67: Modified Duration | Q67: =Q66/(1+$C$6) -> 20.071326 | AA67: Modified Duration | AB67: =AB66/(1+$C$6) -> 43.511574
E68: Convexity | F68: =M64/H64 -> 1506.9299 | P68: Convexity | Q68: =X64/S64 -> 767.64579 | AA68: Convexity | AB68: =AI64/AD64 -> 2515.8499
E69: GBP01 | F69: =H64*F67*0.0001 -> 0.26261617 | P69: GBP01 | Q69: =S64*Q67*0.0001 -> 0.10843705 | AA69: GBP01 | AB69: =AD64*AB67*0.0001 -> 0.92165471

Sheet Dashboard
B1: Measuring and Communicating Interest Rate Risk : DV01 & Convexity in UK Bond Markets
B4: Presented By: | C4: Ayan Biswas
B24: Bond Maturity (Years) | C24: Yield
B25: 1 | C25: 0.03772
B26: 3 | C26: 0.03799
B27: 5 | C27: 0.03961
B28: 10 | C28: 0.04518
B29: 15 | C29: 0.04916
B30: 20 | C30: 0.05164
B31: 30 | C31: 0.0527
B32: 50 | C32: 0.0474
